<?xml version="1.0" encoding="UTF-8" standalone="no"?><author age_group="xx" gender="xx" lang="EN" type="twitter" url="https://twitter.com/PakoRho">
	<documents count="128">
		<document id="327040300180705280" url="https://twitter.com/PakoRho/status/327040300180705280"><![CDATA[<a href="/Mikelgro" class="twitter-atreply pretty-link js-nav" dir="ltr" data-mentioned-user-id="45207129" ><s>@</s><b>Mikelgro</b></a> <a href="/gastronfo" class="twitter-atreply pretty-link js-nav" dir="ltr" data-mentioned-user-id="142807993" ><s>@</s><b>gastronfo</b></a> <a href="/Charls337" class="twitter-atreply pretty-link js-nav" dir="ltr" data-mentioned-user-id="55583364" ><s>@</s><b>charls337</b></a> psssss!]]></document>
		<document id="330026262628274176" url="https://twitter.com/PakoRho/status/330026262628274176"><![CDATA[Saps on soc? <a href="http://t.co/9Vde9nqA4i" rel="nofollow noopener" dir="ltr" data-expanded-url="http://instagram.com/p/Y0cbefuQp6/" class="twitter-timeline-link" target="_blank" title="http://instagram.com/p/Y0cbefuQp6/" ><span class="tco-ellipsis"></span><span class="invisible">http://</span><span class="js-display-url">instagram.com/p/Y0cbefuQp6/</span><span class="invisible"></span><span class="tco-ellipsis"><span class="invisible">&nbsp;</span></span></a>]]></document>
		<document id="331668326944239616" url="https://twitter.com/PakoRho/status/331668326944239616"><![CDATA[The Year that SharePoint Died?<a href="http://t.co/MdA1jJkpZ1" rel="nofollow noopener" dir="ltr" data-expanded-url="http://blog.furuknap.net/the-year-that-sharepoint-died" class="twitter-timeline-link u-hidden" target="_blank" title="http://blog.furuknap.net/the-year-that-sharepoint-died" ><span class="tco-ellipsis"></span><span class="invisible">http://</span><span class="js-display-url">blog.furuknap.net/the-year-that-</span><span class="invisible">sharepoint-died</span><span class="tco-ellipsis"><span class="invisible">&nbsp;</span>…</span></a>]]></document>
		<document id="332556810751967232" url="https://twitter.com/PakoRho/status/332556810751967232"><![CDATA[<a href="/CristinaPlumed" class="twitter-atreply pretty-link js-nav" dir="ltr" data-mentioned-user-id="180425449" ><s>@</s><b>CristinaPlumed</b></a> buena foto]]></document>
		<document id="332799424973643777" url="https://twitter.com/PakoRho/status/332799424973643777"><![CDATA[Email Marketing in your SharePoint by <a href="/deividasu" class="twitter-atreply pretty-link js-nav" dir="ltr" data-mentioned-user-id="60376899" ><s>@</s><b>deividasu</b></a> on <a href="/SlideShare" class="twitter-atreply pretty-link js-nav" dir="ltr" data-mentioned-user-id="9676152" ><s>@</s><b>slideshare</b></a><a href="http://t.co/DZsrATwzmw" rel="nofollow noopener" dir="ltr" data-expanded-url="http://www.slideshare.net/deividasu/e-mail-marketing-in-your-share-point" class="twitter-timeline-link u-hidden" target="_blank" title="http://www.slideshare.net/deividasu/e-mail-marketing-in-your-share-point" ><span class="tco-ellipsis"></span><span class="invisible">http://www.</span><span class="js-display-url">slideshare.net/deividasu/e-ma</span><span class="invisible">il-marketing-in-your-share-point</span><span class="tco-ellipsis"><span class="invisible">&nbsp;</span>…</span></a>]]></document>
		<document id="332799473300406272" url="https://twitter.com/PakoRho/status/332799473300406272"><![CDATA[E-mail marketing from your SharePoint | SharePoint Catalog <a href="http://t.co/sk4pzsR0Kg" rel="nofollow noopener" dir="ltr" data-expanded-url="http://sharepoint-catalog.com/2013/05/10/e-mail-marketing-from-your-sharepoint/" class="twitter-timeline-link" target="_blank" title="http://sharepoint-catalog.com/2013/05/10/e-mail-marketing-from-your-sharepoint/" ><span class="tco-ellipsis"></span><span class="invisible">http://</span><span class="js-display-url">sharepoint-catalog.com/2013/05/10/e-m</span><span class="invisible">ail-marketing-from-your-sharepoint/</span><span class="tco-ellipsis"><span class="invisible">&nbsp;</span>…</span></a>]]></document>
		<document id="332826276316471297" url="https://twitter.com/PakoRho/status/332826276316471297"><![CDATA[<a href="/ggtort" class="twitter-atreply pretty-link js-nav" dir="ltr" data-mentioned-user-id="4013941" ><s>@</s><b>ggtort</b></a> en mi oficina]]></document>
		<document id="332877229023440896" url="https://twitter.com/PakoRho/status/332877229023440896"><![CDATA[My <a href="/klout" class="twitter-atreply pretty-link js-nav" dir="ltr" data-mentioned-user-id="15134782" ><s>@</s><b>Klout</b></a> Score has climbed from 63 to 64!<a href="http://t.co/VJBnvuJVkf" rel="nofollow noopener" dir="ltr" data-expanded-url="http://klout.com/user/PakoRho/score-analysis?n=tw&amp;v=mobile_change" class="twitter-timeline-link u-hidden" target="_blank" title="http://klout.com/user/PakoRho/score-analysis?n=tw&amp;v=mobile_change" ><span class="tco-ellipsis"></span><span class="invisible">http://</span><span class="js-display-url">klout.com/user/PakoRho/s</span><span class="invisible">core-analysis?n=tw&amp;v=mobile_change</span><span class="tco-ellipsis"><span class="invisible">&nbsp;</span>…</span></a>]]></document>
		<document id="332886196944531456" url="https://twitter.com/PakoRho/status/332886196944531456"><![CDATA[<a href="/Ortiz_Tani" class="twitter-atreply pretty-link js-nav" dir="ltr" data-mentioned-user-id="470118871" ><s>@</s><b>Ortiz_Tani</b></a> <a href="/cafjk" class="twitter-atreply pretty-link js-nav" dir="ltr" data-mentioned-user-id="144936523" ><s>@</s><b>cafjk</b></a> <a href="/gastronfo" class="twitter-atreply pretty-link js-nav" dir="ltr" data-mentioned-user-id="142807993" ><s>@</s><b>gastronfo</b></a> <a href="/palbeme" class="twitter-atreply pretty-link js-nav" dir="ltr" data-mentioned-user-id="92844463" ><s>@</s><b>palbeme</b></a> <a href="/ggtort" class="twitter-atreply pretty-link js-nav" dir="ltr" data-mentioned-user-id="4013941" ><s>@</s><b>ggtort</b></a> <a href="/Charls337" class="twitter-atreply pretty-link js-nav" dir="ltr" data-mentioned-user-id="55583364" ><s>@</s><b>Charls337</b></a> <a href="/sonia_brines" class="twitter-atreply pretty-link js-nav" dir="ltr" data-mentioned-user-id="943590877" ><s>@</s><b>sonia_brines</b></a> <a href="/CristinaPlumed" class="twitter-atreply pretty-link js-nav" dir="ltr" data-mentioned-user-id="180425449" ><s>@</s><b>CristinaPlumed</b></a> <a href="/Mikelgro" class="twitter-atreply pretty-link js-nav" dir="ltr" data-mentioned-user-id="45207129" ><s>@</s><b>Mikelgro</b></a> <a href="/albertllueca" class="twitter-atreply pretty-link js-nav" dir="ltr" data-mentioned-user-id="36027330" ><s>@</s><b>albertllueca</b></a> ola ke ase]]></document>
		<document id="332997316548124672" url="https://twitter.com/PakoRho/status/332997316548124672"><![CDATA[I gave <a href="/AdrianDiaz81" class="twitter-atreply pretty-link js-nav" dir="ltr" data-mentioned-user-id="435268143" ><s>@</s><b>AdrianDiaz81</b></a> +K about Microsoft Sharepoint on <a href="/klout" class="twitter-atreply pretty-link js-nav" dir="ltr" data-mentioned-user-id="15134782" ><s>@</s><b>klout</b></a><a href="http://t.co/U5lU4VjvTW" rel="nofollow noopener" dir="ltr" data-expanded-url="http://klout.com/plusk/gave/topic/34902901876880244/66146625450848308/7915355120401101475?n=tw&amp;v=plusk_gave" class="twitter-timeline-link u-hidden" target="_blank" title="http://klout.com/plusk/gave/topic/34902901876880244/66146625450848308/7915355120401101475?n=tw&amp;v=plusk_gave" ><span class="tco-ellipsis"></span><span class="invisible">http://</span><span class="js-display-url">klout.com/plusk/gave/top</span><span class="invisible">ic/34902901876880244/66146625450848308/7915355120401101475?n=tw&amp;v=plusk_gave</span><span class="tco-ellipsis"><span class="invisible">&nbsp;</span>…</span></a>]]></document>
		<document id="339398210114162690" url="https://twitter.com/PakoRho/status/339398210114162690"><![CDATA[Thank you <a href="/ejecutiva" class="twitter-atreply pretty-link js-nav" dir="ltr" data-mentioned-user-id="20197130" ><s>@</s><b>ejecutiva</b></a> for giving me +K about Valencia!<a href="http://t.co/ZcaPngOZoK" rel="nofollow noopener" dir="ltr" data-expanded-url="http://klout.com/user/PakoRho/topics?n=tw&amp;v=plusK_thanks&amp;i=34902901876880244" class="twitter-timeline-link u-hidden" target="_blank" title="http://klout.com/user/PakoRho/topics?n=tw&amp;v=plusK_thanks&amp;i=34902901876880244" ><span class="tco-ellipsis"></span><span class="invisible">http://</span><span class="js-display-url">klout.com/user/PakoRho/t</span><span class="invisible">opics?n=tw&amp;v=plusK_thanks&amp;i=34902901876880244</span><span class="tco-ellipsis"><span class="invisible">&nbsp;</span>…</span></a>]]></document>
		<document id="339398521633517568" url="https://twitter.com/PakoRho/status/339398521633517568"><![CDATA[I gave <a href="/ejecutiva" class="twitter-atreply pretty-link js-nav" dir="ltr" data-mentioned-user-id="20197130" ><s>@</s><b>ejecutiva</b></a> +K about Trading on <a href="/klout" class="twitter-atreply pretty-link js-nav" dir="ltr" data-mentioned-user-id="15134782" ><s>@</s><b>klout</b></a><a href="http://t.co/X80UNnJMnl" rel="nofollow noopener" dir="ltr" data-expanded-url="http://klout.com/ejecutiva/topics?n=tw&amp;v=plusk_gave&amp;i=34902901876880244" class="twitter-timeline-link u-hidden" target="_blank" title="http://klout.com/ejecutiva/topics?n=tw&amp;v=plusk_gave&amp;i=34902901876880244" ><span class="tco-ellipsis"></span><span class="invisible">http://</span><span class="js-display-url">klout.com/ejecutiva/topi</span><span class="invisible">cs?n=tw&amp;v=plusk_gave&amp;i=34902901876880244</span><span class="tco-ellipsis"><span class="invisible">&nbsp;</span>…</span></a>]]></document>
		<document id="341678018646925312" url="https://twitter.com/PakoRho/status/341678018646925312"><![CDATA[<a href="/CristinaPlumed" class="twitter-atreply pretty-link js-nav" dir="ltr" data-mentioned-user-id="180425449" ><s>@</s><b>CristinaPlumed</b></a> <a href="/cafjk" class="twitter-atreply pretty-link js-nav" dir="ltr" data-mentioned-user-id="144936523" ><s>@</s><b>cafjk</b></a> <a href="/Charls337" class="twitter-atreply pretty-link js-nav" dir="ltr" data-mentioned-user-id="55583364" ><s>@</s><b>Charls337</b></a> <a href="/sonia_brines" class="twitter-atreply pretty-link js-nav" dir="ltr" data-mentioned-user-id="943590877" ><s>@</s><b>sonia_brines</b></a> <a href="/DaviniaBono" class="twitter-atreply pretty-link js-nav" dir="ltr" data-mentioned-user-id="229941851" ><s>@</s><b>DaviniaBono</b></a> <a href="/ggtort" class="twitter-atreply pretty-link js-nav" dir="ltr" data-mentioned-user-id="4013941" ><s>@</s><b>ggtort</b></a> <a href="/palbeme" class="twitter-atreply pretty-link js-nav" dir="ltr" data-mentioned-user-id="92844463" ><s>@</s><b>palbeme</b></a> <a href="/lauracasans" class="twitter-atreply pretty-link js-nav" dir="ltr" data-mentioned-user-id="332096000" ><s>@</s><b>lauracasans</b></a> <a href="/Ortiz_Tani" class="twitter-atreply pretty-link js-nav" dir="ltr" data-mentioned-user-id="470118871" ><s>@</s><b>Ortiz_Tani</b></a> Ok... Amorcito con a/a]]></document>
		<document id="341865043224309760" url="https://twitter.com/PakoRho/status/341865043224309760"><![CDATA[<a href="/CristinaPlumed" class="twitter-atreply pretty-link js-nav" dir="ltr" data-mentioned-user-id="180425449" ><s>@</s><b>CristinaPlumed</b></a> <a href="/cafjk" class="twitter-atreply pretty-link js-nav" dir="ltr" data-mentioned-user-id="144936523" ><s>@</s><b>cafjk</b></a> <a href="/albertllueca" class="twitter-atreply pretty-link js-nav" dir="ltr" data-mentioned-user-id="36027330" ><s>@</s><b>albertllueca</b></a> <a href="/gastronfo" class="twitter-atreply pretty-link js-nav" dir="ltr" data-mentioned-user-id="142807993" ><s>@</s><b>gastronfo</b></a> <a href="/palbeme" class="twitter-atreply pretty-link js-nav" dir="ltr" data-mentioned-user-id="92844463" ><s>@</s><b>palbeme</b></a> <a href="/sonia_brines" class="twitter-atreply pretty-link js-nav" dir="ltr" data-mentioned-user-id="943590877" ><s>@</s><b>sonia_brines</b></a> <a href="/ggtort" class="twitter-atreply pretty-link js-nav" dir="ltr" data-mentioned-user-id="4013941" ><s>@</s><b>ggtort</b></a> <a href="/Charls337" class="twitter-atreply pretty-link js-nav" dir="ltr" data-mentioned-user-id="55583364" ><s>@</s><b>Charls337</b></a> vale, vale!!]]></document>
		<document id="341891024752361473" url="https://twitter.com/PakoRho/status/341891024752361473"><![CDATA[<a href="/GTISoftware" class="twitter-atreply pretty-link js-nav" dir="ltr" data-mentioned-user-id="138327970" ><s>@</s><b>GTISoftware</b></a>]]></document>
		<document id="342009424690413570" url="https://twitter.com/PakoRho/status/342009424690413570"><![CDATA[<a href="/cafjk" class="twitter-atreply pretty-link js-nav" dir="ltr" data-mentioned-user-id="144936523" ><s>@</s><b>cafjk</b></a> <a href="/ggtort" class="twitter-atreply pretty-link js-nav" dir="ltr" data-mentioned-user-id="4013941" ><s>@</s><b>ggtort</b></a> <a href="/palbeme" class="twitter-atreply pretty-link js-nav" dir="ltr" data-mentioned-user-id="92844463" ><s>@</s><b>palbeme</b></a> <a href="/CristinaPlumed" class="twitter-atreply pretty-link js-nav" dir="ltr" data-mentioned-user-id="180425449" ><s>@</s><b>CristinaPlumed</b></a> <a href="/Charls337" class="twitter-atreply pretty-link js-nav" dir="ltr" data-mentioned-user-id="55583364" ><s>@</s><b>Charls337</b></a> <a href="/gastronfo" class="twitter-atreply pretty-link js-nav" dir="ltr" data-mentioned-user-id="142807993" ><s>@</s><b>gastronfo</b></a> avanti tutti]]></document>
		<document id="342013394288791552" url="https://twitter.com/PakoRho/status/342013394288791552"><![CDATA[<a href="/palbeme" class="twitter-atreply pretty-link js-nav" dir="ltr" data-mentioned-user-id="92844463" ><s>@</s><b>palbeme</b></a> <a href="/cafjk" class="twitter-atreply pretty-link js-nav" dir="ltr" data-mentioned-user-id="144936523" ><s>@</s><b>cafjk</b></a> <a href="/ggtort" class="twitter-atreply pretty-link js-nav" dir="ltr" data-mentioned-user-id="4013941" ><s>@</s><b>ggtort</b></a> <a href="/sonia_brines" class="twitter-atreply pretty-link js-nav" dir="ltr" data-mentioned-user-id="943590877" ><s>@</s><b>sonia_brines</b></a> <a href="/CristinaPlumed" class="twitter-atreply pretty-link js-nav" dir="ltr" data-mentioned-user-id="180425449" ><s>@</s><b>CristinaPlumed</b></a> <a href="/Charls337" class="twitter-atreply pretty-link js-nav" dir="ltr" data-mentioned-user-id="55583364" ><s>@</s><b>Charls337</b></a> <a href="/gastronfo" class="twitter-atreply pretty-link js-nav" dir="ltr" data-mentioned-user-id="142807993" ><s>@</s><b>gastronfo</b></a> no valen excusas]]></document>
		<document id="342037975091253248" url="https://twitter.com/PakoRho/status/342037975091253248"><![CDATA[<a href="/CristinaPlumed" class="twitter-atreply pretty-link js-nav" dir="ltr" data-mentioned-user-id="180425449" ><s>@</s><b>CristinaPlumed</b></a> bona nit!]]></document>
		<document id="342978375591264257" url="https://twitter.com/PakoRho/status/342978375591264257"><![CDATA[<a href="/gomezcamara" class="twitter-atreply pretty-link js-nav" dir="ltr" data-mentioned-user-id="17288095" ><s>@</s><b>gomezcamara</b></a> <a href="/cafjk" class="twitter-atreply pretty-link js-nav" dir="ltr" data-mentioned-user-id="144936523" ><s>@</s><b>cafjk</b></a> <a href="/CristinaPlumed" class="twitter-atreply pretty-link js-nav" dir="ltr" data-mentioned-user-id="180425449" ><s>@</s><b>CristinaPlumed</b></a> <a href="/palbeme" class="twitter-atreply pretty-link js-nav" dir="ltr" data-mentioned-user-id="92844463" ><s>@</s><b>palbeme</b></a> <a href="/ggtort" class="twitter-atreply pretty-link js-nav" dir="ltr" data-mentioned-user-id="4013941" ><s>@</s><b>ggtort</b></a> <a href="/sonia_brines" class="twitter-atreply pretty-link js-nav" dir="ltr" data-mentioned-user-id="943590877" ><s>@</s><b>sonia_brines</b></a> <a href="/Charls337" class="twitter-atreply pretty-link js-nav" dir="ltr" data-mentioned-user-id="55583364" ><s>@</s><b>Charls337</b></a> <a href="/gastronfo" class="twitter-atreply pretty-link js-nav" dir="ltr" data-mentioned-user-id="142807993" ><s>@</s><b>gastronfo</b></a> no corráis...]]></document>
		<document id="343661135322566656" url="https://twitter.com/PakoRho/status/343661135322566656"><![CDATA[I received +K about Microsoft from <a href="/ejecutiva" class="twitter-atreply pretty-link js-nav" dir="ltr" data-mentioned-user-id="20197130" ><s>@</s><b>ejecutiva</b></a>. Thanks!<a href="http://t.co/VorIgcH4Q7" rel="nofollow noopener" dir="ltr" data-expanded-url="http://klout.com/user/PakoRho/topics?n=tw&amp;v=mobile_plusK_thanks" class="twitter-timeline-link u-hidden" target="_blank" title="http://klout.com/user/PakoRho/topics?n=tw&amp;v=mobile_plusK_thanks" ><span class="tco-ellipsis"></span><span class="invisible">http://</span><span class="js-display-url">klout.com/user/PakoRho/t</span><span class="invisible">opics?n=tw&amp;v=mobile_plusK_thanks</span><span class="tco-ellipsis"><span class="invisible">&nbsp;</span>…</span></a>]]></document>
		<document id="343755512573206528" url="https://twitter.com/PakoRho/status/343755512573206528"><![CDATA[<a href="/vescrig" class="twitter-atreply pretty-link js-nav" dir="ltr" data-mentioned-user-id="5163671" ><s>@</s><b>vescrig</b></a> of course... 19:30]]></document>
		<document id="344918366470938625" url="https://twitter.com/PakoRho/status/344918366470938625"><![CDATA[<a href="/sonia_brines" class="twitter-atreply pretty-link js-nav" dir="ltr" data-mentioned-user-id="943590877" ><s>@</s><b>sonia_brines</b></a> <a href="/gomezcamara" class="twitter-atreply pretty-link js-nav" dir="ltr" data-mentioned-user-id="17288095" ><s>@</s><b>gomezcamara</b></a> <a href="/cafjk" class="twitter-atreply pretty-link js-nav" dir="ltr" data-mentioned-user-id="144936523" ><s>@</s><b>cafjk</b></a> <a href="/palbeme" class="twitter-atreply pretty-link js-nav" dir="ltr" data-mentioned-user-id="92844463" ><s>@</s><b>palbeme</b></a> <a href="/CristinaPlumed" class="twitter-atreply pretty-link js-nav" dir="ltr" data-mentioned-user-id="180425449" ><s>@</s><b>CristinaPlumed</b></a> <a href="/Charls337" class="twitter-atreply pretty-link js-nav" dir="ltr" data-mentioned-user-id="55583364" ><s>@</s><b>Charls337</b></a> <a href="/gastronfo" class="twitter-atreply pretty-link js-nav" dir="ltr" data-mentioned-user-id="142807993" ><s>@</s><b>gastronfo</b></a> <a href="/Mikelgro" class="twitter-atreply pretty-link js-nav" dir="ltr" data-mentioned-user-id="45207129" ><s>@</s><b>Mikelgro</b></a> <a href="/albertllueca" class="twitter-atreply pretty-link js-nav" dir="ltr" data-mentioned-user-id="36027330" ><s>@</s><b>albertllueca</b></a> <a href="/ggtort" class="twitter-atreply pretty-link js-nav" dir="ltr" data-mentioned-user-id="4013941" ><s>@</s><b>ggtort</b></a> Yo tengo. Comida DAGE 27]]></document>
		<document id="345139472737923072" url="https://twitter.com/PakoRho/status/345139472737923072"><![CDATA[<a href="/cafjk" class="twitter-atreply pretty-link js-nav" dir="ltr" data-mentioned-user-id="144936523" ><s>@</s><b>cafjk</b></a> <a href="/Charls337" class="twitter-atreply pretty-link js-nav" dir="ltr" data-mentioned-user-id="55583364" ><s>@</s><b>Charls337</b></a> <a href="/ggtort" class="twitter-atreply pretty-link js-nav" dir="ltr" data-mentioned-user-id="4013941" ><s>@</s><b>ggtort</b></a> <a href="/sonia_brines" class="twitter-atreply pretty-link js-nav" dir="ltr" data-mentioned-user-id="943590877" ><s>@</s><b>sonia_brines</b></a> <a href="/albertllueca" class="twitter-atreply pretty-link js-nav" dir="ltr" data-mentioned-user-id="36027330" ><s>@</s><b>albertllueca</b></a> <a href="/palbeme" class="twitter-atreply pretty-link js-nav" dir="ltr" data-mentioned-user-id="92844463" ><s>@</s><b>palbeme</b></a> <a href="/CristinaPlumed" class="twitter-atreply pretty-link js-nav" dir="ltr" data-mentioned-user-id="180425449" ><s>@</s><b>CristinaPlumed</b></a> <a href="/gastronfo" class="twitter-atreply pretty-link js-nav" dir="ltr" data-mentioned-user-id="142807993" ><s>@</s><b>gastronfo</b></a> <a href="/Mikelgro" class="twitter-atreply pretty-link js-nav" dir="ltr" data-mentioned-user-id="45207129" ><s>@</s><b>Mikelgro</b></a> Haber almorzado ;)]]></document>
		<document id="345239804721627136" url="https://twitter.com/PakoRho/status/345239804721627136"><![CDATA[<a href="/MariolaCorega" class="twitter-atreply pretty-link js-nav" dir="ltr" data-mentioned-user-id="66687707" ><s>@</s><b>MariolaCorega</b></a> of course <a href="/BelenSanz" class="twitter-atreply pretty-link js-nav" dir="ltr" data-mentioned-user-id="14774987" ><s>@</s><b>BelenSanz</b></a>]]></document>
		<document id="345253902712725504" url="https://twitter.com/PakoRho/status/345253902712725504"><![CDATA[I gave <a href="/ejecutiva" class="twitter-atreply pretty-link js-nav" dir="ltr" data-mentioned-user-id="20197130" ><s>@</s><b>ejecutiva</b></a> +K about Apple on <a href="/klout" class="twitter-atreply pretty-link js-nav" dir="ltr" data-mentioned-user-id="15134782" ><s>@</s><b>klout</b></a><a href="http://t.co/72kxRqXu1i" rel="nofollow noopener" dir="ltr" data-expanded-url="http://klout.com/plusk/gave/topic/34902901876880244/38843551551299411/8283952755688430877?n=tw&amp;v=plusk_gave" class="twitter-timeline-link u-hidden" target="_blank" title="http://klout.com/plusk/gave/topic/34902901876880244/38843551551299411/8283952755688430877?n=tw&amp;v=plusk_gave" ><span class="tco-ellipsis"></span><span class="invisible">http://</span><span class="js-display-url">klout.com/plusk/gave/top</span><span class="invisible">ic/34902901876880244/38843551551299411/8283952755688430877?n=tw&amp;v=plusk_gave</span><span class="tco-ellipsis"><span class="invisible">&nbsp;</span>…</span></a>]]></document>
		<document id="345468965730009088" url="https://twitter.com/PakoRho/status/345468965730009088"><![CDATA[<a href="/cafjk" class="twitter-atreply pretty-link js-nav" dir="ltr" data-mentioned-user-id="144936523" ><s>@</s><b>cafjk</b></a> <a href="/gomezcamara" class="twitter-atreply pretty-link js-nav" dir="ltr" data-mentioned-user-id="17288095" ><s>@</s><b>gomezcamara</b></a> <a href="/sonia_brines" class="twitter-atreply pretty-link js-nav" dir="ltr" data-mentioned-user-id="943590877" ><s>@</s><b>sonia_brines</b></a> <a href="/Charls337" class="twitter-atreply pretty-link js-nav" dir="ltr" data-mentioned-user-id="55583364" ><s>@</s><b>Charls337</b></a> <a href="/ggtort" class="twitter-atreply pretty-link js-nav" dir="ltr" data-mentioned-user-id="4013941" ><s>@</s><b>ggtort</b></a> <a href="/palbeme" class="twitter-atreply pretty-link js-nav" dir="ltr" data-mentioned-user-id="92844463" ><s>@</s><b>palbeme</b></a> <a href="/CristinaPlumed" class="twitter-atreply pretty-link js-nav" dir="ltr" data-mentioned-user-id="180425449" ><s>@</s><b>CristinaPlumed</b></a> <a href="/gastronfo" class="twitter-atreply pretty-link js-nav" dir="ltr" data-mentioned-user-id="142807993" ><s>@</s><b>gastronfo</b></a> <a href="/Mikelgro" class="twitter-atreply pretty-link js-nav" dir="ltr" data-mentioned-user-id="45207129" ><s>@</s><b>Mikelgro</b></a> <a href="/albertllueca" class="twitter-atreply pretty-link js-nav" dir="ltr" data-mentioned-user-id="36027330" ><s>@</s><b>albertllueca</b></a> ¡basta ya!]]></document>
		<document id="345696820556607488" url="https://twitter.com/PakoRho/status/345696820556607488"><![CDATA[I gave <a href="/ejecutiva" class="twitter-atreply pretty-link js-nav" dir="ltr" data-mentioned-user-id="20197130" ><s>@</s><b>ejecutiva</b></a> +K about Blogging on <a href="/klout" class="twitter-atreply pretty-link js-nav" dir="ltr" data-mentioned-user-id="15134782" ><s>@</s><b>klout</b></a><a href="http://t.co/Nr65ARm2kC" rel="nofollow noopener" dir="ltr" data-expanded-url="http://klout.com/plusk/gave/topic/34902901876880244/38843551551299411/7331299376965973530?n=tw&amp;v=plusk_gave" class="twitter-timeline-link u-hidden" target="_blank" title="http://klout.com/plusk/gave/topic/34902901876880244/38843551551299411/7331299376965973530?n=tw&amp;v=plusk_gave" ><span class="tco-ellipsis"></span><span class="invisible">http://</span><span class="js-display-url">klout.com/plusk/gave/top</span><span class="invisible">ic/34902901876880244/38843551551299411/7331299376965973530?n=tw&amp;v=plusk_gave</span><span class="tco-ellipsis"><span class="invisible">&nbsp;</span>…</span></a>]]></document>
		<document id="346888087739179008" url="https://twitter.com/PakoRho/status/346888087739179008"><![CDATA[Thank you <a href="/lanzanet" class="twitter-atreply pretty-link js-nav" dir="ltr" data-mentioned-user-id="335839594" ><s>@</s><b>lanzanet</b></a> for giving me +K about Microsoft!<a href="http://t.co/ZcaPngOZoK" rel="nofollow noopener" dir="ltr" data-expanded-url="http://klout.com/user/PakoRho/topics?n=tw&amp;v=plusK_thanks&amp;i=34902901876880244" class="twitter-timeline-link u-hidden" target="_blank" title="http://klout.com/user/PakoRho/topics?n=tw&amp;v=plusK_thanks&amp;i=34902901876880244" ><span class="tco-ellipsis"></span><span class="invisible">http://</span><span class="js-display-url">klout.com/user/PakoRho/t</span><span class="invisible">opics?n=tw&amp;v=plusK_thanks&amp;i=34902901876880244</span><span class="tco-ellipsis"><span class="invisible">&nbsp;</span>…</span></a>]]></document>
		<document id="348429522158379008" url="https://twitter.com/PakoRho/status/348429522158379008"><![CDATA[Man (at <a href="/SanLucarFruits" class="twitter-atreply pretty-link js-nav" dir="ltr" data-mentioned-user-id="239293998" ><s>@</s><b>SanLucarFruits</b></a>)<a href="http://t.co/LCW4gX5Mk5" rel="nofollow noopener" dir="ltr" data-expanded-url="http://4sq.com/11UeJLg" class="twitter-timeline-link u-hidden" target="_blank" title="http://4sq.com/11UeJLg" ><span class="tco-ellipsis"></span><span class="invisible">http://</span><span class="js-display-url">4sq.com/11UeJLg</span><span class="invisible"></span><span class="tco-ellipsis"><span class="invisible">&nbsp;</span></span></a>]]></document>
		<document id="348806901242396672" url="https://twitter.com/PakoRho/status/348806901242396672"><![CDATA[I received +K about Klout from <a href="/ejecutiva" class="twitter-atreply pretty-link js-nav" dir="ltr" data-mentioned-user-id="20197130" ><s>@</s><b>ejecutiva</b></a>. Thanks!<a href="http://t.co/VorIgcH4Q7" rel="nofollow noopener" dir="ltr" data-expanded-url="http://klout.com/user/PakoRho/topics?n=tw&amp;v=mobile_plusK_thanks" class="twitter-timeline-link u-hidden" target="_blank" title="http://klout.com/user/PakoRho/topics?n=tw&amp;v=mobile_plusK_thanks" ><span class="tco-ellipsis"></span><span class="invisible">http://</span><span class="js-display-url">klout.com/user/PakoRho/t</span><span class="invisible">opics?n=tw&amp;v=mobile_plusK_thanks</span><span class="tco-ellipsis"><span class="invisible">&nbsp;</span>…</span></a>]]></document>
		<document id="353976307547246592" url="https://twitter.com/PakoRho/status/353976307547246592"><![CDATA[<a href="/byppol" class="twitter-atreply pretty-link js-nav" dir="ltr" data-mentioned-user-id="216444543" ><s>@</s><b>byppol</b></a> Gracies!!!]]></document>
		<document id="358649770622980096" url="https://twitter.com/PakoRho/status/358649770622980096"><![CDATA[Passejant. (@ Estany D&#39;Ivars) [pic]:<a href="http://t.co/VN7MnuB1Pc" rel="nofollow noopener" dir="ltr" data-expanded-url="http://4sq.com/126VEet" class="twitter-timeline-link u-hidden" target="_blank" title="http://4sq.com/126VEet" ><span class="tco-ellipsis"></span><span class="invisible">http://</span><span class="js-display-url">4sq.com/126VEet</span><span class="invisible"></span><span class="tco-ellipsis"><span class="invisible">&nbsp;</span></span></a>]]></document>
		<document id="362260483471978496" url="https://twitter.com/PakoRho/status/362260483471978496"><![CDATA[[Apps] Integrando Yammer con SharePoint 2013 - Desarrollando sobre SharePoint <a href="http://t.co/PZQoxkcB2u" rel="nofollow noopener" dir="ltr" data-expanded-url="http://blogs.encamina.com/desarrollandosobresharepoint/2013/07/30/apps-integrando-yammer-con-sharepoint-2013/" class="twitter-timeline-link" target="_blank" title="http://blogs.encamina.com/desarrollandosobresharepoint/2013/07/30/apps-integrando-yammer-con-sharepoint-2013/" ><span class="tco-ellipsis"></span><span class="invisible">http://</span><span class="js-display-url">blogs.encamina.com/desarrollandos</span><span class="invisible">obresharepoint/2013/07/30/apps-integrando-yammer-con-sharepoint-2013/</span><span class="tco-ellipsis"><span class="invisible">&nbsp;</span>…</span></a> <a href="/AdrianDiaz81" class="twitter-atreply pretty-link js-nav" dir="ltr" data-mentioned-user-id="435268143" ><s>@</s><b>adriandiaz81</b></a>]]></document>
		<document id="365441890423799809" url="https://twitter.com/PakoRho/status/365441890423799809"><![CDATA[ENCAMINA tras la Microsoft World Partner Conference 2013 <a href="http://t.co/k2bx3hUaSA" rel="nofollow noopener" dir="ltr" data-expanded-url="http://blogs.encamina.com/en-las-nubes/2013/08/08/tras-la-microsoft-world-partner-conference-2013/" class="twitter-timeline-link" target="_blank" title="http://blogs.encamina.com/en-las-nubes/2013/08/08/tras-la-microsoft-world-partner-conference-2013/" ><span class="tco-ellipsis"></span><span class="invisible">http://</span><span class="js-display-url">blogs.encamina.com/en-las-nubes/2</span><span class="invisible">013/08/08/tras-la-microsoft-world-partner-conference-2013/</span><span class="tco-ellipsis"><span class="invisible">&nbsp;</span>…</span></a>]]></document>
		<document id="377119131822088192" url="https://twitter.com/PakoRho/status/377119131822088192"><![CDATA[<a href="/Chessimo_Chess" class="twitter-atreply pretty-link js-nav" dir="ltr" data-mentioned-user-id="207198469" ><s>@</s><b>Chessimo_Chess</b></a> I need to pay twice to enjoy the app on my iPad and on my iPhone. Bad business :(]]></document>
		<document id="377452159895224320" url="https://twitter.com/PakoRho/status/377452159895224320"><![CDATA[Thank you <a href="/ejecutiva" class="twitter-atreply pretty-link js-nav" dir="ltr" data-mentioned-user-id="20197130" ><s>@</s><b>ejecutiva</b></a> for giving me +K about Software Development!<a href="http://t.co/ZcaPngOZoK" rel="nofollow noopener" dir="ltr" data-expanded-url="http://klout.com/user/PakoRho/topics?n=tw&amp;v=plusK_thanks&amp;i=34902901876880244" class="twitter-timeline-link u-hidden" target="_blank" title="http://klout.com/user/PakoRho/topics?n=tw&amp;v=plusK_thanks&amp;i=34902901876880244" ><span class="tco-ellipsis"></span><span class="invisible">http://</span><span class="js-display-url">klout.com/user/PakoRho/t</span><span class="invisible">opics?n=tw&amp;v=plusK_thanks&amp;i=34902901876880244</span><span class="tco-ellipsis"><span class="invisible">&nbsp;</span>…</span></a>]]></document>
		<document id="377773008427175936" url="https://twitter.com/PakoRho/status/377773008427175936"><![CDATA[I received +K about Business from <a href="/mhbuch" class="twitter-atreply pretty-link js-nav" dir="ltr" data-mentioned-user-id="124834378" ><s>@</s><b>mhbuch</b></a>. Thanks!<a href="http://t.co/nh4iUofXEe" rel="nofollow noopener" dir="ltr" data-expanded-url="http://klout.com/user/PakoRho/topics?n=tw&amp;v=mobile_plusK_thanks" class="twitter-timeline-link u-hidden" target="_blank" title="http://klout.com/user/PakoRho/topics?n=tw&amp;v=mobile_plusK_thanks" ><span class="tco-ellipsis"></span><span class="invisible">http://</span><span class="js-display-url">klout.com/user/PakoRho/t</span><span class="invisible">opics?n=tw&amp;v=mobile_plusK_thanks</span><span class="tco-ellipsis"><span class="invisible">&nbsp;</span>…</span></a>]]></document>
		<document id="382531274269003776" url="https://twitter.com/PakoRho/status/382531274269003776"><![CDATA[I received +K about Software Development from <a href="/mhbuch" class="twitter-atreply pretty-link js-nav" dir="ltr" data-mentioned-user-id="124834378" ><s>@</s><b>mhbuch</b></a>. Thanks!<a href="http://t.co/nh4iUofXEe" rel="nofollow noopener" dir="ltr" data-expanded-url="http://klout.com/user/PakoRho/topics?n=tw&amp;v=mobile_plusK_thanks" class="twitter-timeline-link u-hidden" target="_blank" title="http://klout.com/user/PakoRho/topics?n=tw&amp;v=mobile_plusK_thanks" ><span class="tco-ellipsis"></span><span class="invisible">http://</span><span class="js-display-url">klout.com/user/PakoRho/t</span><span class="invisible">opics?n=tw&amp;v=mobile_plusK_thanks</span><span class="tco-ellipsis"><span class="invisible">&nbsp;</span>…</span></a>]]></document>
		<document id="382533412550373376" url="https://twitter.com/PakoRho/status/382533412550373376"><![CDATA[I gave <a href="/gomezcamara" class="twitter-atreply pretty-link js-nav" dir="ltr" data-mentioned-user-id="17288095" ><s>@</s><b>gomezcamara</b></a> +K about Business on <a href="/klout" class="twitter-atreply pretty-link js-nav" dir="ltr" data-mentioned-user-id="15134782" ><s>@</s><b>klout</b></a><a href="http://t.co/Cz0g6oGI2i" rel="nofollow noopener" dir="ltr" data-expanded-url="http://klout.com/plusk/gave/topic/34902901876880244/85568398087804326/6011700363202204797?n=tw&amp;v=plusk_gave" class="twitter-timeline-link u-hidden" target="_blank" title="http://klout.com/plusk/gave/topic/34902901876880244/85568398087804326/6011700363202204797?n=tw&amp;v=plusk_gave" ><span class="tco-ellipsis"></span><span class="invisible">http://</span><span class="js-display-url">klout.com/plusk/gave/top</span><span class="invisible">ic/34902901876880244/85568398087804326/6011700363202204797?n=tw&amp;v=plusk_gave</span><span class="tco-ellipsis"><span class="invisible">&nbsp;</span>…</span></a>]]></document>
		<document id="387962527029530624" url="https://twitter.com/PakoRho/status/387962527029530624"><![CDATA[Help internet-driven economic growth transform the lives of millions. <a href="http://t.co/7ETNR5pSSI" rel="nofollow noopener" dir="ltr" data-expanded-url="http://startupmanifesto.eu/" class="twitter-timeline-link" target="_blank" title="http://startupmanifesto.eu/" ><span class="tco-ellipsis"></span><span class="invisible">http://</span><span class="js-display-url">startupmanifesto.eu</span><span class="invisible">/</span><span class="tco-ellipsis"><span class="invisible">&nbsp;</span></span></a> <a href="/hashtag/startupmanifesto?src=hash" data-query-source="hashtag_click" class="twitter-hashtag pretty-link js-nav" dir="ltr" ><s>#</s><b>startupmanifesto</b></a>]]></document>
		<document id="395839520999890944" url="https://twitter.com/PakoRho/status/395839520999890944"><![CDATA[The ethics of quality - return «value»; <a href="http://t.co/iXAWYxOiJq" rel="nofollow noopener" dir="ltr" data-expanded-url="http://bit.ly/17YLnyt" class="twitter-timeline-link" target="_blank" title="http://bit.ly/17YLnyt" ><span class="tco-ellipsis"></span><span class="invisible">http://</span><span class="js-display-url">bit.ly/17YLnyt</span><span class="invisible"></span><span class="tco-ellipsis"><span class="invisible">&nbsp;</span></span></a> by <a href="/soyrochus" class="twitter-atreply pretty-link js-nav" dir="ltr" data-mentioned-user-id="14934628" ><s>@</s><b>soyrochus</b></a>]]></document>
		<document id="399238921961209856" url="https://twitter.com/PakoRho/status/399238921961209856"><![CDATA[Thank you <a href="/ejecutiva" class="twitter-atreply pretty-link js-nav" dir="ltr" data-mentioned-user-id="20197130" ><s>@</s><b>ejecutiva</b></a> for giving me +K about Business Intelligence! <a href="http://t.co/ZcaPngOZoK" rel="nofollow noopener" dir="ltr" data-expanded-url="http://klout.com/user/PakoRho/topics?n=tw&amp;v=plusK_thanks&amp;i=34902901876880244" class="twitter-timeline-link" target="_blank" title="http://klout.com/user/PakoRho/topics?n=tw&amp;v=plusK_thanks&amp;i=34902901876880244" ><span class="tco-ellipsis"></span><span class="invisible">http://</span><span class="js-display-url">klout.com/user/PakoRho/t</span><span class="invisible">opics?n=tw&amp;v=plusK_thanks&amp;i=34902901876880244</span><span class="tco-ellipsis"><span class="invisible">&nbsp;</span>…</span></a> Justo el martes doy una charla sobre BI ;)]]></document>
		<document id="401255814951747584" url="https://twitter.com/PakoRho/status/401255814951747584"><![CDATA[<a href="/albertllueca" class="twitter-atreply pretty-link js-nav" dir="ltr" data-mentioned-user-id="36027330" ><s>@</s><b>albertllueca</b></a> <a href="/palbeme" class="twitter-atreply pretty-link js-nav" dir="ltr" data-mentioned-user-id="92844463" ><s>@</s><b>palbeme</b></a> <a href="/ASECAM1" class="twitter-atreply pretty-link js-nav" dir="ltr" data-mentioned-user-id="576985931" ><s>@</s><b>ASECAM1</b></a> YouTube? On?]]></document>
		<document id="402449006292639744" url="https://twitter.com/PakoRho/status/402449006292639744"><![CDATA[<a href="/ejecutiva" class="twitter-atreply pretty-link js-nav" dir="ltr" data-mentioned-user-id="20197130" ><s>@</s><b>ejecutiva</b></a> Microsoft Power!!!]]></document>
		<document id="403489162399326208" url="https://twitter.com/PakoRho/status/403489162399326208"><![CDATA[<a href="/Lukre76" class="twitter-atreply pretty-link js-nav" dir="ltr" data-mentioned-user-id="575330940" ><s>@</s><b>Lukre76</b></a> primer Twitt!!! Enhorabuena!]]></document>
		<document id="417614485398884352" url="https://twitter.com/PakoRho/status/417614485398884352"><![CDATA[Yammer y Microsoft Dynamics CRM <a href="http://t.co/j6IXNwgJ0j" rel="nofollow noopener" dir="ltr" data-expanded-url="http://bit.ly/19mhw46" class="twitter-timeline-link" target="_blank" title="http://bit.ly/19mhw46" ><span class="tco-ellipsis"></span><span class="invisible">http://</span><span class="js-display-url">bit.ly/19mhw46</span><span class="invisible"></span><span class="tco-ellipsis"><span class="invisible">&nbsp;</span></span></a>]]></document>
		<document id="327040300180705280" url="https://twitter.com/PakoRho/status/327040300180705280"><![CDATA[<a href="/Mikelgro" class="twitter-atreply pretty-link js-nav" dir="ltr" data-mentioned-user-id="45207129" ><s>@</s><b>Mikelgro</b></a> <a href="/gastronfo" class="twitter-atreply pretty-link js-nav" dir="ltr" data-mentioned-user-id="142807993" ><s>@</s><b>gastronfo</b></a> <a href="/Charls337" class="twitter-atreply pretty-link js-nav" dir="ltr" data-mentioned-user-id="55583364" ><s>@</s><b>charls337</b></a> psssss!]]></document>
		<document id="330026262628274176" url="https://twitter.com/PakoRho/status/330026262628274176"><![CDATA[Saps on soc? <a href="http://t.co/9Vde9nqA4i" rel="nofollow noopener" dir="ltr" data-expanded-url="http://instagram.com/p/Y0cbefuQp6/" class="twitter-timeline-link" target="_blank" title="http://instagram.com/p/Y0cbefuQp6/" ><span class="tco-ellipsis"></span><span class="invisible">http://</span><span class="js-display-url">instagram.com/p/Y0cbefuQp6/</span><span class="invisible"></span><span class="tco-ellipsis"><span class="invisible">&nbsp;</span></span></a>]]></document>
		<document id="331668326944239616" url="https://twitter.com/PakoRho/status/331668326944239616"><![CDATA[The Year that SharePoint Died?<a href="http://t.co/MdA1jJkpZ1" rel="nofollow noopener" dir="ltr" data-expanded-url="http://blog.furuknap.net/the-year-that-sharepoint-died" class="twitter-timeline-link u-hidden" target="_blank" title="http://blog.furuknap.net/the-year-that-sharepoint-died" ><span class="tco-ellipsis"></span><span class="invisible">http://</span><span class="js-display-url">blog.furuknap.net/the-year-that-</span><span class="invisible">sharepoint-died</span><span class="tco-ellipsis"><span class="invisible">&nbsp;</span>…</span></a>]]></document>
		<document id="332556810751967232" url="https://twitter.com/PakoRho/status/332556810751967232"><![CDATA[<a href="/CristinaPlumed" class="twitter-atreply pretty-link js-nav" dir="ltr" data-mentioned-user-id="180425449" ><s>@</s><b>CristinaPlumed</b></a> buena foto]]></document>
		<document id="332799424973643777" url="https://twitter.com/PakoRho/status/332799424973643777"><![CDATA[Email Marketing in your SharePoint by <a href="/deividasu" class="twitter-atreply pretty-link js-nav" dir="ltr" data-mentioned-user-id="60376899" ><s>@</s><b>deividasu</b></a> on <a href="/SlideShare" class="twitter-atreply pretty-link js-nav" dir="ltr" data-mentioned-user-id="9676152" ><s>@</s><b>slideshare</b></a><a href="http://t.co/DZsrATwzmw" rel="nofollow noopener" dir="ltr" data-expanded-url="http://www.slideshare.net/deividasu/e-mail-marketing-in-your-share-point" class="twitter-timeline-link u-hidden" target="_blank" title="http://www.slideshare.net/deividasu/e-mail-marketing-in-your-share-point" ><span class="tco-ellipsis"></span><span class="invisible">http://www.</span><span class="js-display-url">slideshare.net/deividasu/e-ma</span><span class="invisible">il-marketing-in-your-share-point</span><span class="tco-ellipsis"><span class="invisible">&nbsp;</span>…</span></a>]]></document>
		<document id="332799473300406272" url="https://twitter.com/PakoRho/status/332799473300406272"><![CDATA[E-mail marketing from your SharePoint | SharePoint Catalog <a href="http://t.co/sk4pzsR0Kg" rel="nofollow noopener" dir="ltr" data-expanded-url="http://sharepoint-catalog.com/2013/05/10/e-mail-marketing-from-your-sharepoint/" class="twitter-timeline-link" target="_blank" title="http://sharepoint-catalog.com/2013/05/10/e-mail-marketing-from-your-sharepoint/" ><span class="tco-ellipsis"></span><span class="invisible">http://</span><span class="js-display-url">sharepoint-catalog.com/2013/05/10/e-m</span><span class="invisible">ail-marketing-from-your-sharepoint/</span><span class="tco-ellipsis"><span class="invisible">&nbsp;</span>…</span></a>]]></document>
		<document id="332826276316471297" url="https://twitter.com/PakoRho/status/332826276316471297"><![CDATA[<a href="/ggtort" class="twitter-atreply pretty-link js-nav" dir="ltr" data-mentioned-user-id="4013941" ><s>@</s><b>ggtort</b></a> en mi oficina]]></document>
		<document id="332877229023440896" url="https://twitter.com/PakoRho/status/332877229023440896"><![CDATA[My <a href="/klout" class="twitter-atreply pretty-link js-nav" dir="ltr" data-mentioned-user-id="15134782" ><s>@</s><b>Klout</b></a> Score has climbed from 63 to 64!<a href="http://t.co/VJBnvuJVkf" rel="nofollow noopener" dir="ltr" data-expanded-url="http://klout.com/user/PakoRho/score-analysis?n=tw&amp;v=mobile_change" class="twitter-timeline-link u-hidden" target="_blank" title="http://klout.com/user/PakoRho/score-analysis?n=tw&amp;v=mobile_change" ><span class="tco-ellipsis"></span><span class="invisible">http://</span><span class="js-display-url">klout.com/user/PakoRho/s</span><span class="invisible">core-analysis?n=tw&amp;v=mobile_change</span><span class="tco-ellipsis"><span class="invisible">&nbsp;</span>…</span></a>]]></document>
		<document id="332886196944531456" url="https://twitter.com/PakoRho/status/332886196944531456"><![CDATA[<a href="/Ortiz_Tani" class="twitter-atreply pretty-link js-nav" dir="ltr" data-mentioned-user-id="470118871" ><s>@</s><b>Ortiz_Tani</b></a> <a href="/cafjk" class="twitter-atreply pretty-link js-nav" dir="ltr" data-mentioned-user-id="144936523" ><s>@</s><b>cafjk</b></a> <a href="/gastronfo" class="twitter-atreply pretty-link js-nav" dir="ltr" data-mentioned-user-id="142807993" ><s>@</s><b>gastronfo</b></a> <a href="/palbeme" class="twitter-atreply pretty-link js-nav" dir="ltr" data-mentioned-user-id="92844463" ><s>@</s><b>palbeme</b></a> <a href="/ggtort" class="twitter-atreply pretty-link js-nav" dir="ltr" data-mentioned-user-id="4013941" ><s>@</s><b>ggtort</b></a> <a href="/Charls337" class="twitter-atreply pretty-link js-nav" dir="ltr" data-mentioned-user-id="55583364" ><s>@</s><b>Charls337</b></a> <a href="/sonia_brines" class="twitter-atreply pretty-link js-nav" dir="ltr" data-mentioned-user-id="943590877" ><s>@</s><b>sonia_brines</b></a> <a href="/CristinaPlumed" class="twitter-atreply pretty-link js-nav" dir="ltr" data-mentioned-user-id="180425449" ><s>@</s><b>CristinaPlumed</b></a> <a href="/Mikelgro" class="twitter-atreply pretty-link js-nav" dir="ltr" data-mentioned-user-id="45207129" ><s>@</s><b>Mikelgro</b></a> <a href="/albertllueca" class="twitter-atreply pretty-link js-nav" dir="ltr" data-mentioned-user-id="36027330" ><s>@</s><b>albertllueca</b></a> ola ke ase]]></document>
		<document id="332997316548124672" url="https://twitter.com/PakoRho/status/332997316548124672"><![CDATA[I gave <a href="/AdrianDiaz81" class="twitter-atreply pretty-link js-nav" dir="ltr" data-mentioned-user-id="435268143" ><s>@</s><b>AdrianDiaz81</b></a> +K about Microsoft Sharepoint on <a href="/klout" class="twitter-atreply pretty-link js-nav" dir="ltr" data-mentioned-user-id="15134782" ><s>@</s><b>klout</b></a><a href="http://t.co/U5lU4VjvTW" rel="nofollow noopener" dir="ltr" data-expanded-url="http://klout.com/plusk/gave/topic/34902901876880244/66146625450848308/7915355120401101475?n=tw&amp;v=plusk_gave" class="twitter-timeline-link u-hidden" target="_blank" title="http://klout.com/plusk/gave/topic/34902901876880244/66146625450848308/7915355120401101475?n=tw&amp;v=plusk_gave" ><span class="tco-ellipsis"></span><span class="invisible">http://</span><span class="js-display-url">klout.com/plusk/gave/top</span><span class="invisible">ic/34902901876880244/66146625450848308/7915355120401101475?n=tw&amp;v=plusk_gave</span><span class="tco-ellipsis"><span class="invisible">&nbsp;</span>…</span></a>]]></document>
		<document id="339398210114162690" url="https://twitter.com/PakoRho/status/339398210114162690"><![CDATA[Thank you <a href="/ejecutiva" class="twitter-atreply pretty-link js-nav" dir="ltr" data-mentioned-user-id="20197130" ><s>@</s><b>ejecutiva</b></a> for giving me +K about Valencia!<a href="http://t.co/ZcaPngOZoK" rel="nofollow noopener" dir="ltr" data-expanded-url="http://klout.com/user/PakoRho/topics?n=tw&amp;v=plusK_thanks&amp;i=34902901876880244" class="twitter-timeline-link u-hidden" target="_blank" title="http://klout.com/user/PakoRho/topics?n=tw&amp;v=plusK_thanks&amp;i=34902901876880244" ><span class="tco-ellipsis"></span><span class="invisible">http://</span><span class="js-display-url">klout.com/user/PakoRho/t</span><span class="invisible">opics?n=tw&amp;v=plusK_thanks&amp;i=34902901876880244</span><span class="tco-ellipsis"><span class="invisible">&nbsp;</span>…</span></a>]]></document>
		<document id="339398521633517568" url="https://twitter.com/PakoRho/status/339398521633517568"><![CDATA[I gave <a href="/ejecutiva" class="twitter-atreply pretty-link js-nav" dir="ltr" data-mentioned-user-id="20197130" ><s>@</s><b>ejecutiva</b></a> +K about Trading on <a href="/klout" class="twitter-atreply pretty-link js-nav" dir="ltr" data-mentioned-user-id="15134782" ><s>@</s><b>klout</b></a><a href="http://t.co/X80UNnJMnl" rel="nofollow noopener" dir="ltr" data-expanded-url="http://klout.com/ejecutiva/topics?n=tw&amp;v=plusk_gave&amp;i=34902901876880244" class="twitter-timeline-link u-hidden" target="_blank" title="http://klout.com/ejecutiva/topics?n=tw&amp;v=plusk_gave&amp;i=34902901876880244" ><span class="tco-ellipsis"></span><span class="invisible">http://</span><span class="js-display-url">klout.com/ejecutiva/topi</span><span class="invisible">cs?n=tw&amp;v=plusk_gave&amp;i=34902901876880244</span><span class="tco-ellipsis"><span class="invisible">&nbsp;</span>…</span></a>]]></document>
		<document id="341678018646925312" url="https://twitter.com/PakoRho/status/341678018646925312"><![CDATA[<a href="/CristinaPlumed" class="twitter-atreply pretty-link js-nav" dir="ltr" data-mentioned-user-id="180425449" ><s>@</s><b>CristinaPlumed</b></a> <a href="/cafjk" class="twitter-atreply pretty-link js-nav" dir="ltr" data-mentioned-user-id="144936523" ><s>@</s><b>cafjk</b></a> <a href="/Charls337" class="twitter-atreply pretty-link js-nav" dir="ltr" data-mentioned-user-id="55583364" ><s>@</s><b>Charls337</b></a> <a href="/sonia_brines" class="twitter-atreply pretty-link js-nav" dir="ltr" data-mentioned-user-id="943590877" ><s>@</s><b>sonia_brines</b></a> <a href="/DaviniaBono" class="twitter-atreply pretty-link js-nav" dir="ltr" data-mentioned-user-id="229941851" ><s>@</s><b>DaviniaBono</b></a> <a href="/ggtort" class="twitter-atreply pretty-link js-nav" dir="ltr" data-mentioned-user-id="4013941" ><s>@</s><b>ggtort</b></a> <a href="/palbeme" class="twitter-atreply pretty-link js-nav" dir="ltr" data-mentioned-user-id="92844463" ><s>@</s><b>palbeme</b></a> <a href="/lauracasans" class="twitter-atreply pretty-link js-nav" dir="ltr" data-mentioned-user-id="332096000" ><s>@</s><b>lauracasans</b></a> <a href="/Ortiz_Tani" class="twitter-atreply pretty-link js-nav" dir="ltr" data-mentioned-user-id="470118871" ><s>@</s><b>Ortiz_Tani</b></a> Ok... Amorcito con a/a]]></document>
		<document id="341865043224309760" url="https://twitter.com/PakoRho/status/341865043224309760"><![CDATA[<a href="/CristinaPlumed" class="twitter-atreply pretty-link js-nav" dir="ltr" data-mentioned-user-id="180425449" ><s>@</s><b>CristinaPlumed</b></a> <a href="/cafjk" class="twitter-atreply pretty-link js-nav" dir="ltr" data-mentioned-user-id="144936523" ><s>@</s><b>cafjk</b></a> <a href="/albertllueca" class="twitter-atreply pretty-link js-nav" dir="ltr" data-mentioned-user-id="36027330" ><s>@</s><b>albertllueca</b></a> <a href="/gastronfo" class="twitter-atreply pretty-link js-nav" dir="ltr" data-mentioned-user-id="142807993" ><s>@</s><b>gastronfo</b></a> <a href="/palbeme" class="twitter-atreply pretty-link js-nav" dir="ltr" data-mentioned-user-id="92844463" ><s>@</s><b>palbeme</b></a> <a href="/sonia_brines" class="twitter-atreply pretty-link js-nav" dir="ltr" data-mentioned-user-id="943590877" ><s>@</s><b>sonia_brines</b></a> <a href="/ggtort" class="twitter-atreply pretty-link js-nav" dir="ltr" data-mentioned-user-id="4013941" ><s>@</s><b>ggtort</b></a> <a href="/Charls337" class="twitter-atreply pretty-link js-nav" dir="ltr" data-mentioned-user-id="55583364" ><s>@</s><b>Charls337</b></a> vale, vale!!]]></document>
		<document id="341891024752361473" url="https://twitter.com/PakoRho/status/341891024752361473"><![CDATA[<a href="/GTISoftware" class="twitter-atreply pretty-link js-nav" dir="ltr" data-mentioned-user-id="138327970" ><s>@</s><b>GTISoftware</b></a>]]></document>
		<document id="342009424690413570" url="https://twitter.com/PakoRho/status/342009424690413570"><![CDATA[<a href="/cafjk" class="twitter-atreply pretty-link js-nav" dir="ltr" data-mentioned-user-id="144936523" ><s>@</s><b>cafjk</b></a> <a href="/ggtort" class="twitter-atreply pretty-link js-nav" dir="ltr" data-mentioned-user-id="4013941" ><s>@</s><b>ggtort</b></a> <a href="/palbeme" class="twitter-atreply pretty-link js-nav" dir="ltr" data-mentioned-user-id="92844463" ><s>@</s><b>palbeme</b></a> <a href="/CristinaPlumed" class="twitter-atreply pretty-link js-nav" dir="ltr" data-mentioned-user-id="180425449" ><s>@</s><b>CristinaPlumed</b></a> <a href="/Charls337" class="twitter-atreply pretty-link js-nav" dir="ltr" data-mentioned-user-id="55583364" ><s>@</s><b>Charls337</b></a> <a href="/gastronfo" class="twitter-atreply pretty-link js-nav" dir="ltr" data-mentioned-user-id="142807993" ><s>@</s><b>gastronfo</b></a> avanti tutti]]></document>
		<document id="342013394288791552" url="https://twitter.com/PakoRho/status/342013394288791552"><![CDATA[<a href="/palbeme" class="twitter-atreply pretty-link js-nav" dir="ltr" data-mentioned-user-id="92844463" ><s>@</s><b>palbeme</b></a> <a href="/cafjk" class="twitter-atreply pretty-link js-nav" dir="ltr" data-mentioned-user-id="144936523" ><s>@</s><b>cafjk</b></a> <a href="/ggtort" class="twitter-atreply pretty-link js-nav" dir="ltr" data-mentioned-user-id="4013941" ><s>@</s><b>ggtort</b></a> <a href="/sonia_brines" class="twitter-atreply pretty-link js-nav" dir="ltr" data-mentioned-user-id="943590877" ><s>@</s><b>sonia_brines</b></a> <a href="/CristinaPlumed" class="twitter-atreply pretty-link js-nav" dir="ltr" data-mentioned-user-id="180425449" ><s>@</s><b>CristinaPlumed</b></a> <a href="/Charls337" class="twitter-atreply pretty-link js-nav" dir="ltr" data-mentioned-user-id="55583364" ><s>@</s><b>Charls337</b></a> <a href="/gastronfo" class="twitter-atreply pretty-link js-nav" dir="ltr" data-mentioned-user-id="142807993" ><s>@</s><b>gastronfo</b></a> no valen excusas]]></document>
		<document id="342037975091253248" url="https://twitter.com/PakoRho/status/342037975091253248"><![CDATA[<a href="/CristinaPlumed" class="twitter-atreply pretty-link js-nav" dir="ltr" data-mentioned-user-id="180425449" ><s>@</s><b>CristinaPlumed</b></a> bona nit!]]></document>
		<document id="342978375591264257" url="https://twitter.com/PakoRho/status/342978375591264257"><![CDATA[<a href="/gomezcamara" class="twitter-atreply pretty-link js-nav" dir="ltr" data-mentioned-user-id="17288095" ><s>@</s><b>gomezcamara</b></a> <a href="/cafjk" class="twitter-atreply pretty-link js-nav" dir="ltr" data-mentioned-user-id="144936523" ><s>@</s><b>cafjk</b></a> <a href="/CristinaPlumed" class="twitter-atreply pretty-link js-nav" dir="ltr" data-mentioned-user-id="180425449" ><s>@</s><b>CristinaPlumed</b></a> <a href="/palbeme" class="twitter-atreply pretty-link js-nav" dir="ltr" data-mentioned-user-id="92844463" ><s>@</s><b>palbeme</b></a> <a href="/ggtort" class="twitter-atreply pretty-link js-nav" dir="ltr" data-mentioned-user-id="4013941" ><s>@</s><b>ggtort</b></a> <a href="/sonia_brines" class="twitter-atreply pretty-link js-nav" dir="ltr" data-mentioned-user-id="943590877" ><s>@</s><b>sonia_brines</b></a> <a href="/Charls337" class="twitter-atreply pretty-link js-nav" dir="ltr" data-mentioned-user-id="55583364" ><s>@</s><b>Charls337</b></a> <a href="/gastronfo" class="twitter-atreply pretty-link js-nav" dir="ltr" data-mentioned-user-id="142807993" ><s>@</s><b>gastronfo</b></a> no corráis...]]></document>
		<document id="343661135322566656" url="https://twitter.com/PakoRho/status/343661135322566656"><![CDATA[I received +K about Microsoft from <a href="/ejecutiva" class="twitter-atreply pretty-link js-nav" dir="ltr" data-mentioned-user-id="20197130" ><s>@</s><b>ejecutiva</b></a>. Thanks!<a href="http://t.co/VorIgcH4Q7" rel="nofollow noopener" dir="ltr" data-expanded-url="http://klout.com/user/PakoRho/topics?n=tw&amp;v=mobile_plusK_thanks" class="twitter-timeline-link u-hidden" target="_blank" title="http://klout.com/user/PakoRho/topics?n=tw&amp;v=mobile_plusK_thanks" ><span class="tco-ellipsis"></span><span class="invisible">http://</span><span class="js-display-url">klout.com/user/PakoRho/t</span><span class="invisible">opics?n=tw&amp;v=mobile_plusK_thanks</span><span class="tco-ellipsis"><span class="invisible">&nbsp;</span>…</span></a>]]></document>
		<document id="343755512573206528" url="https://twitter.com/PakoRho/status/343755512573206528"><![CDATA[<a href="/vescrig" class="twitter-atreply pretty-link js-nav" dir="ltr" data-mentioned-user-id="5163671" ><s>@</s><b>vescrig</b></a> of course... 19:30]]></document>
		<document id="344918366470938625" url="https://twitter.com/PakoRho/status/344918366470938625"><![CDATA[<a href="/sonia_brines" class="twitter-atreply pretty-link js-nav" dir="ltr" data-mentioned-user-id="943590877" ><s>@</s><b>sonia_brines</b></a> <a href="/gomezcamara" class="twitter-atreply pretty-link js-nav" dir="ltr" data-mentioned-user-id="17288095" ><s>@</s><b>gomezcamara</b></a> <a href="/cafjk" class="twitter-atreply pretty-link js-nav" dir="ltr" data-mentioned-user-id="144936523" ><s>@</s><b>cafjk</b></a> <a href="/palbeme" class="twitter-atreply pretty-link js-nav" dir="ltr" data-mentioned-user-id="92844463" ><s>@</s><b>palbeme</b></a> <a href="/CristinaPlumed" class="twitter-atreply pretty-link js-nav" dir="ltr" data-mentioned-user-id="180425449" ><s>@</s><b>CristinaPlumed</b></a> <a href="/Charls337" class="twitter-atreply pretty-link js-nav" dir="ltr" data-mentioned-user-id="55583364" ><s>@</s><b>Charls337</b></a> <a href="/gastronfo" class="twitter-atreply pretty-link js-nav" dir="ltr" data-mentioned-user-id="142807993" ><s>@</s><b>gastronfo</b></a> <a href="/Mikelgro" class="twitter-atreply pretty-link js-nav" dir="ltr" data-mentioned-user-id="45207129" ><s>@</s><b>Mikelgro</b></a> <a href="/albertllueca" class="twitter-atreply pretty-link js-nav" dir="ltr" data-mentioned-user-id="36027330" ><s>@</s><b>albertllueca</b></a> <a href="/ggtort" class="twitter-atreply pretty-link js-nav" dir="ltr" data-mentioned-user-id="4013941" ><s>@</s><b>ggtort</b></a> Yo tengo. Comida DAGE 27]]></document>
		<document id="345139472737923072" url="https://twitter.com/PakoRho/status/345139472737923072"><![CDATA[<a href="/cafjk" class="twitter-atreply pretty-link js-nav" dir="ltr" data-mentioned-user-id="144936523" ><s>@</s><b>cafjk</b></a> <a href="/Charls337" class="twitter-atreply pretty-link js-nav" dir="ltr" data-mentioned-user-id="55583364" ><s>@</s><b>Charls337</b></a> <a href="/ggtort" class="twitter-atreply pretty-link js-nav" dir="ltr" data-mentioned-user-id="4013941" ><s>@</s><b>ggtort</b></a> <a href="/sonia_brines" class="twitter-atreply pretty-link js-nav" dir="ltr" data-mentioned-user-id="943590877" ><s>@</s><b>sonia_brines</b></a> <a href="/albertllueca" class="twitter-atreply pretty-link js-nav" dir="ltr" data-mentioned-user-id="36027330" ><s>@</s><b>albertllueca</b></a> <a href="/palbeme" class="twitter-atreply pretty-link js-nav" dir="ltr" data-mentioned-user-id="92844463" ><s>@</s><b>palbeme</b></a> <a href="/CristinaPlumed" class="twitter-atreply pretty-link js-nav" dir="ltr" data-mentioned-user-id="180425449" ><s>@</s><b>CristinaPlumed</b></a> <a href="/gastronfo" class="twitter-atreply pretty-link js-nav" dir="ltr" data-mentioned-user-id="142807993" ><s>@</s><b>gastronfo</b></a> <a href="/Mikelgro" class="twitter-atreply pretty-link js-nav" dir="ltr" data-mentioned-user-id="45207129" ><s>@</s><b>Mikelgro</b></a> Haber almorzado ;)]]></document>
		<document id="345239804721627136" url="https://twitter.com/PakoRho/status/345239804721627136"><![CDATA[<a href="/MariolaCorega" class="twitter-atreply pretty-link js-nav" dir="ltr" data-mentioned-user-id="66687707" ><s>@</s><b>MariolaCorega</b></a> of course <a href="/BelenSanz" class="twitter-atreply pretty-link js-nav" dir="ltr" data-mentioned-user-id="14774987" ><s>@</s><b>BelenSanz</b></a>]]></document>
		<document id="345253902712725504" url="https://twitter.com/PakoRho/status/345253902712725504"><![CDATA[I gave <a href="/ejecutiva" class="twitter-atreply pretty-link js-nav" dir="ltr" data-mentioned-user-id="20197130" ><s>@</s><b>ejecutiva</b></a> +K about Apple on <a href="/klout" class="twitter-atreply pretty-link js-nav" dir="ltr" data-mentioned-user-id="15134782" ><s>@</s><b>klout</b></a><a href="http://t.co/72kxRqXu1i" rel="nofollow noopener" dir="ltr" data-expanded-url="http://klout.com/plusk/gave/topic/34902901876880244/38843551551299411/8283952755688430877?n=tw&amp;v=plusk_gave" class="twitter-timeline-link u-hidden" target="_blank" title="http://klout.com/plusk/gave/topic/34902901876880244/38843551551299411/8283952755688430877?n=tw&amp;v=plusk_gave" ><span class="tco-ellipsis"></span><span class="invisible">http://</span><span class="js-display-url">klout.com/plusk/gave/top</span><span class="invisible">ic/34902901876880244/38843551551299411/8283952755688430877?n=tw&amp;v=plusk_gave</span><span class="tco-ellipsis"><span class="invisible">&nbsp;</span>…</span></a>]]></document>
		<document id="345468965730009088" url="https://twitter.com/PakoRho/status/345468965730009088"><![CDATA[<a href="/cafjk" class="twitter-atreply pretty-link js-nav" dir="ltr" data-mentioned-user-id="144936523" ><s>@</s><b>cafjk</b></a> <a href="/gomezcamara" class="twitter-atreply pretty-link js-nav" dir="ltr" data-mentioned-user-id="17288095" ><s>@</s><b>gomezcamara</b></a> <a href="/sonia_brines" class="twitter-atreply pretty-link js-nav" dir="ltr" data-mentioned-user-id="943590877" ><s>@</s><b>sonia_brines</b></a> <a href="/Charls337" class="twitter-atreply pretty-link js-nav" dir="ltr" data-mentioned-user-id="55583364" ><s>@</s><b>Charls337</b></a> <a href="/ggtort" class="twitter-atreply pretty-link js-nav" dir="ltr" data-mentioned-user-id="4013941" ><s>@</s><b>ggtort</b></a> <a href="/palbeme" class="twitter-atreply pretty-link js-nav" dir="ltr" data-mentioned-user-id="92844463" ><s>@</s><b>palbeme</b></a> <a href="/CristinaPlumed" class="twitter-atreply pretty-link js-nav" dir="ltr" data-mentioned-user-id="180425449" ><s>@</s><b>CristinaPlumed</b></a> <a href="/gastronfo" class="twitter-atreply pretty-link js-nav" dir="ltr" data-mentioned-user-id="142807993" ><s>@</s><b>gastronfo</b></a> <a href="/Mikelgro" class="twitter-atreply pretty-link js-nav" dir="ltr" data-mentioned-user-id="45207129" ><s>@</s><b>Mikelgro</b></a> <a href="/albertllueca" class="twitter-atreply pretty-link js-nav" dir="ltr" data-mentioned-user-id="36027330" ><s>@</s><b>albertllueca</b></a> ¡basta ya!]]></document>
		<document id="345696820556607488" url="https://twitter.com/PakoRho/status/345696820556607488"><![CDATA[I gave <a href="/ejecutiva" class="twitter-atreply pretty-link js-nav" dir="ltr" data-mentioned-user-id="20197130" ><s>@</s><b>ejecutiva</b></a> +K about Blogging on <a href="/klout" class="twitter-atreply pretty-link js-nav" dir="ltr" data-mentioned-user-id="15134782" ><s>@</s><b>klout</b></a><a href="http://t.co/Nr65ARm2kC" rel="nofollow noopener" dir="ltr" data-expanded-url="http://klout.com/plusk/gave/topic/34902901876880244/38843551551299411/7331299376965973530?n=tw&amp;v=plusk_gave" class="twitter-timeline-link u-hidden" target="_blank" title="http://klout.com/plusk/gave/topic/34902901876880244/38843551551299411/7331299376965973530?n=tw&amp;v=plusk_gave" ><span class="tco-ellipsis"></span><span class="invisible">http://</span><span class="js-display-url">klout.com/plusk/gave/top</span><span class="invisible">ic/34902901876880244/38843551551299411/7331299376965973530?n=tw&amp;v=plusk_gave</span><span class="tco-ellipsis"><span class="invisible">&nbsp;</span>…</span></a>]]></document>
		<document id="346888087739179008" url="https://twitter.com/PakoRho/status/346888087739179008"><![CDATA[Thank you <a href="/lanzanet" class="twitter-atreply pretty-link js-nav" dir="ltr" data-mentioned-user-id="335839594" ><s>@</s><b>lanzanet</b></a> for giving me +K about Microsoft!<a href="http://t.co/ZcaPngOZoK" rel="nofollow noopener" dir="ltr" data-expanded-url="http://klout.com/user/PakoRho/topics?n=tw&amp;v=plusK_thanks&amp;i=34902901876880244" class="twitter-timeline-link u-hidden" target="_blank" title="http://klout.com/user/PakoRho/topics?n=tw&amp;v=plusK_thanks&amp;i=34902901876880244" ><span class="tco-ellipsis"></span><span class="invisible">http://</span><span class="js-display-url">klout.com/user/PakoRho/t</span><span class="invisible">opics?n=tw&amp;v=plusK_thanks&amp;i=34902901876880244</span><span class="tco-ellipsis"><span class="invisible">&nbsp;</span>…</span></a>]]></document>
		<document id="348429522158379008" url="https://twitter.com/PakoRho/status/348429522158379008"><![CDATA[Man (at <a href="/SanLucarFruits" class="twitter-atreply pretty-link js-nav" dir="ltr" data-mentioned-user-id="239293998" ><s>@</s><b>SanLucarFruits</b></a>)<a href="http://t.co/LCW4gX5Mk5" rel="nofollow noopener" dir="ltr" data-expanded-url="http://4sq.com/11UeJLg" class="twitter-timeline-link u-hidden" target="_blank" title="http://4sq.com/11UeJLg" ><span class="tco-ellipsis"></span><span class="invisible">http://</span><span class="js-display-url">4sq.com/11UeJLg</span><span class="invisible"></span><span class="tco-ellipsis"><span class="invisible">&nbsp;</span></span></a>]]></document>
		<document id="348806901242396672" url="https://twitter.com/PakoRho/status/348806901242396672"><![CDATA[I received +K about Klout from <a href="/ejecutiva" class="twitter-atreply pretty-link js-nav" dir="ltr" data-mentioned-user-id="20197130" ><s>@</s><b>ejecutiva</b></a>. Thanks!<a href="http://t.co/VorIgcH4Q7" rel="nofollow noopener" dir="ltr" data-expanded-url="http://klout.com/user/PakoRho/topics?n=tw&amp;v=mobile_plusK_thanks" class="twitter-timeline-link u-hidden" target="_blank" title="http://klout.com/user/PakoRho/topics?n=tw&amp;v=mobile_plusK_thanks" ><span class="tco-ellipsis"></span><span class="invisible">http://</span><span class="js-display-url">klout.com/user/PakoRho/t</span><span class="invisible">opics?n=tw&amp;v=mobile_plusK_thanks</span><span class="tco-ellipsis"><span class="invisible">&nbsp;</span>…</span></a>]]></document>
		<document id="353976307547246592" url="https://twitter.com/PakoRho/status/353976307547246592"><![CDATA[<a href="/byppol" class="twitter-atreply pretty-link js-nav" dir="ltr" data-mentioned-user-id="216444543" ><s>@</s><b>byppol</b></a> Gracies!!!]]></document>
		<document id="358649770622980096" url="https://twitter.com/PakoRho/status/358649770622980096"><![CDATA[Passejant. (@ Estany D&#39;Ivars) [pic]:<a href="http://t.co/VN7MnuB1Pc" rel="nofollow noopener" dir="ltr" data-expanded-url="http://4sq.com/126VEet" class="twitter-timeline-link u-hidden" target="_blank" title="http://4sq.com/126VEet" ><span class="tco-ellipsis"></span><span class="invisible">http://</span><span class="js-display-url">4sq.com/126VEet</span><span class="invisible"></span><span class="tco-ellipsis"><span class="invisible">&nbsp;</span></span></a>]]></document>
		<document id="362260483471978496" url="https://twitter.com/PakoRho/status/362260483471978496"><![CDATA[[Apps] Integrando Yammer con SharePoint 2013 - Desarrollando sobre SharePoint <a href="http://t.co/PZQoxkcB2u" rel="nofollow noopener" dir="ltr" data-expanded-url="http://blogs.encamina.com/desarrollandosobresharepoint/2013/07/30/apps-integrando-yammer-con-sharepoint-2013/" class="twitter-timeline-link" target="_blank" title="http://blogs.encamina.com/desarrollandosobresharepoint/2013/07/30/apps-integrando-yammer-con-sharepoint-2013/" ><span class="tco-ellipsis"></span><span class="invisible">http://</span><span class="js-display-url">blogs.encamina.com/desarrollandos</span><span class="invisible">obresharepoint/2013/07/30/apps-integrando-yammer-con-sharepoint-2013/</span><span class="tco-ellipsis"><span class="invisible">&nbsp;</span>…</span></a> <a href="/AdrianDiaz81" class="twitter-atreply pretty-link js-nav" dir="ltr" data-mentioned-user-id="435268143" ><s>@</s><b>adriandiaz81</b></a>]]></document>
		<document id="365441890423799809" url="https://twitter.com/PakoRho/status/365441890423799809"><![CDATA[ENCAMINA tras la Microsoft World Partner Conference 2013 <a href="http://t.co/k2bx3hUaSA" rel="nofollow noopener" dir="ltr" data-expanded-url="http://blogs.encamina.com/en-las-nubes/2013/08/08/tras-la-microsoft-world-partner-conference-2013/" class="twitter-timeline-link" target="_blank" title="http://blogs.encamina.com/en-las-nubes/2013/08/08/tras-la-microsoft-world-partner-conference-2013/" ><span class="tco-ellipsis"></span><span class="invisible">http://</span><span class="js-display-url">blogs.encamina.com/en-las-nubes/2</span><span class="invisible">013/08/08/tras-la-microsoft-world-partner-conference-2013/</span><span class="tco-ellipsis"><span class="invisible">&nbsp;</span>…</span></a>]]></document>
		<document id="377119131822088192" url="https://twitter.com/PakoRho/status/377119131822088192"><![CDATA[<a href="/Chessimo_Chess" class="twitter-atreply pretty-link js-nav" dir="ltr" data-mentioned-user-id="207198469" ><s>@</s><b>Chessimo_Chess</b></a> I need to pay twice to enjoy the app on my iPad and on my iPhone. Bad business :(]]></document>
		<document id="377452159895224320" url="https://twitter.com/PakoRho/status/377452159895224320"><![CDATA[Thank you <a href="/ejecutiva" class="twitter-atreply pretty-link js-nav" dir="ltr" data-mentioned-user-id="20197130" ><s>@</s><b>ejecutiva</b></a> for giving me +K about Software Development!<a href="http://t.co/ZcaPngOZoK" rel="nofollow noopener" dir="ltr" data-expanded-url="http://klout.com/user/PakoRho/topics?n=tw&amp;v=plusK_thanks&amp;i=34902901876880244" class="twitter-timeline-link u-hidden" target="_blank" title="http://klout.com/user/PakoRho/topics?n=tw&amp;v=plusK_thanks&amp;i=34902901876880244" ><span class="tco-ellipsis"></span><span class="invisible">http://</span><span class="js-display-url">klout.com/user/PakoRho/t</span><span class="invisible">opics?n=tw&amp;v=plusK_thanks&amp;i=34902901876880244</span><span class="tco-ellipsis"><span class="invisible">&nbsp;</span>…</span></a>]]></document>
		<document id="377773008427175936" url="https://twitter.com/PakoRho/status/377773008427175936"><![CDATA[I received +K about Business from <a href="/mhbuch" class="twitter-atreply pretty-link js-nav" dir="ltr" data-mentioned-user-id="124834378" ><s>@</s><b>mhbuch</b></a>. Thanks!<a href="http://t.co/nh4iUofXEe" rel="nofollow noopener" dir="ltr" data-expanded-url="http://klout.com/user/PakoRho/topics?n=tw&amp;v=mobile_plusK_thanks" class="twitter-timeline-link u-hidden" target="_blank" title="http://klout.com/user/PakoRho/topics?n=tw&amp;v=mobile_plusK_thanks" ><span class="tco-ellipsis"></span><span class="invisible">http://</span><span class="js-display-url">klout.com/user/PakoRho/t</span><span class="invisible">opics?n=tw&amp;v=mobile_plusK_thanks</span><span class="tco-ellipsis"><span class="invisible">&nbsp;</span>…</span></a>]]></document>
		<document id="382531274269003776" url="https://twitter.com/PakoRho/status/382531274269003776"><![CDATA[I received +K about Software Development from <a href="/mhbuch" class="twitter-atreply pretty-link js-nav" dir="ltr" data-mentioned-user-id="124834378" ><s>@</s><b>mhbuch</b></a>. Thanks!<a href="http://t.co/nh4iUofXEe" rel="nofollow noopener" dir="ltr" data-expanded-url="http://klout.com/user/PakoRho/topics?n=tw&amp;v=mobile_plusK_thanks" class="twitter-timeline-link u-hidden" target="_blank" title="http://klout.com/user/PakoRho/topics?n=tw&amp;v=mobile_plusK_thanks" ><span class="tco-ellipsis"></span><span class="invisible">http://</span><span class="js-display-url">klout.com/user/PakoRho/t</span><span class="invisible">opics?n=tw&amp;v=mobile_plusK_thanks</span><span class="tco-ellipsis"><span class="invisible">&nbsp;</span>…</span></a>]]></document>
		<document id="382533412550373376" url="https://twitter.com/PakoRho/status/382533412550373376"><![CDATA[I gave <a href="/gomezcamara" class="twitter-atreply pretty-link js-nav" dir="ltr" data-mentioned-user-id="17288095" ><s>@</s><b>gomezcamara</b></a> +K about Business on <a href="/klout" class="twitter-atreply pretty-link js-nav" dir="ltr" data-mentioned-user-id="15134782" ><s>@</s><b>klout</b></a><a href="http://t.co/Cz0g6oGI2i" rel="nofollow noopener" dir="ltr" data-expanded-url="http://klout.com/plusk/gave/topic/34902901876880244/85568398087804326/6011700363202204797?n=tw&amp;v=plusk_gave" class="twitter-timeline-link u-hidden" target="_blank" title="http://klout.com/plusk/gave/topic/34902901876880244/85568398087804326/6011700363202204797?n=tw&amp;v=plusk_gave" ><span class="tco-ellipsis"></span><span class="invisible">http://</span><span class="js-display-url">klout.com/plusk/gave/top</span><span class="invisible">ic/34902901876880244/85568398087804326/6011700363202204797?n=tw&amp;v=plusk_gave</span><span class="tco-ellipsis"><span class="invisible">&nbsp;</span>…</span></a>]]></document>
		<document id="387962527029530624" url="https://twitter.com/PakoRho/status/387962527029530624"><![CDATA[Help internet-driven economic growth transform the lives of millions. <a href="http://t.co/7ETNR5pSSI" rel="nofollow noopener" dir="ltr" data-expanded-url="http://startupmanifesto.eu/" class="twitter-timeline-link" target="_blank" title="http://startupmanifesto.eu/" ><span class="tco-ellipsis"></span><span class="invisible">http://</span><span class="js-display-url">startupmanifesto.eu</span><span class="invisible">/</span><span class="tco-ellipsis"><span class="invisible">&nbsp;</span></span></a> <a href="/hashtag/startupmanifesto?src=hash" data-query-source="hashtag_click" class="twitter-hashtag pretty-link js-nav" dir="ltr" ><s>#</s><b>startupmanifesto</b></a>]]></document>
		<document id="395839520999890944" url="https://twitter.com/PakoRho/status/395839520999890944"><![CDATA[The ethics of quality - return «value»; <a href="http://t.co/iXAWYxOiJq" rel="nofollow noopener" dir="ltr" data-expanded-url="http://bit.ly/17YLnyt" class="twitter-timeline-link" target="_blank" title="http://bit.ly/17YLnyt" ><span class="tco-ellipsis"></span><span class="invisible">http://</span><span class="js-display-url">bit.ly/17YLnyt</span><span class="invisible"></span><span class="tco-ellipsis"><span class="invisible">&nbsp;</span></span></a> by <a href="/soyrochus" class="twitter-atreply pretty-link js-nav" dir="ltr" data-mentioned-user-id="14934628" ><s>@</s><b>soyrochus</b></a>]]></document>
		<document id="399238921961209856" url="https://twitter.com/PakoRho/status/399238921961209856"><![CDATA[Thank you <a href="/ejecutiva" class="twitter-atreply pretty-link js-nav" dir="ltr" data-mentioned-user-id="20197130" ><s>@</s><b>ejecutiva</b></a> for giving me +K about Business Intelligence! <a href="http://t.co/ZcaPngOZoK" rel="nofollow noopener" dir="ltr" data-expanded-url="http://klout.com/user/PakoRho/topics?n=tw&amp;v=plusK_thanks&amp;i=34902901876880244" class="twitter-timeline-link" target="_blank" title="http://klout.com/user/PakoRho/topics?n=tw&amp;v=plusK_thanks&amp;i=34902901876880244" ><span class="tco-ellipsis"></span><span class="invisible">http://</span><span class="js-display-url">klout.com/user/PakoRho/t</span><span class="invisible">opics?n=tw&amp;v=plusK_thanks&amp;i=34902901876880244</span><span class="tco-ellipsis"><span class="invisible">&nbsp;</span>…</span></a> Justo el martes doy una charla sobre BI ;)]]></document>
		<document id="401255814951747584" url="https://twitter.com/PakoRho/status/401255814951747584"><![CDATA[<a href="/albertllueca" class="twitter-atreply pretty-link js-nav" dir="ltr" data-mentioned-user-id="36027330" ><s>@</s><b>albertllueca</b></a> <a href="/palbeme" class="twitter-atreply pretty-link js-nav" dir="ltr" data-mentioned-user-id="92844463" ><s>@</s><b>palbeme</b></a> <a href="/ASECAM1" class="twitter-atreply pretty-link js-nav" dir="ltr" data-mentioned-user-id="576985931" ><s>@</s><b>ASECAM1</b></a> YouTube? On?]]></document>
		<document id="402449006292639744" url="https://twitter.com/PakoRho/status/402449006292639744"><![CDATA[<a href="/ejecutiva" class="twitter-atreply pretty-link js-nav" dir="ltr" data-mentioned-user-id="20197130" ><s>@</s><b>ejecutiva</b></a> Microsoft Power!!!]]></document>
		<document id="403489162399326208" url="https://twitter.com/PakoRho/status/403489162399326208"><![CDATA[<a href="/Lukre76" class="twitter-atreply pretty-link js-nav" dir="ltr" data-mentioned-user-id="575330940" ><s>@</s><b>Lukre76</b></a> primer Twitt!!! Enhorabuena!]]></document>
		<document id="417614485398884352" url="https://twitter.com/PakoRho/status/417614485398884352"><![CDATA[Yammer y Microsoft Dynamics CRM <a href="http://t.co/j6IXNwgJ0j" rel="nofollow noopener" dir="ltr" data-expanded-url="http://bit.ly/19mhw46" class="twitter-timeline-link" target="_blank" title="http://bit.ly/19mhw46" ><span class="tco-ellipsis"></span><span class="invisible">http://</span><span class="js-display-url">bit.ly/19mhw46</span><span class="invisible"></span><span class="tco-ellipsis"><span class="invisible">&nbsp;</span></span></a>]]></document>
	</documents>
</author>