<?xml version="1.0" encoding="UTF-8" standalone="no"?><author age_group="xx" gender="xx" lang="EN" type="twitter" url="https://twitter.com/LauraHarders">
	<documents count="51">
		<document id="212168393015562240" url="https://twitter.com/LauraHarders/status/212168393015562240"><![CDATA[Great to see <a href="/DCMosquitoSquad" class="twitter-atreply pretty-link js-nav" dir="ltr" data-mentioned-user-id="116802083" ><s>@</s><b>DCMosquitoSquad</b></a> featured in <a href="/washingtonpost" class="twitter-atreply pretty-link js-nav" dir="ltr" data-mentioned-user-id="2467791" ><s>@</s><b>WashingtonPost</b></a> by <a href="/addedvalueth" class="twitter-atreply pretty-link js-nav" dir="ltr" data-mentioned-user-id="21792943" ><s>@</s><b>AddedValueTH</b></a>! Bugs are the big losers in this business<a href="http://t.co/REkpxdr0" rel="nofollow noopener" dir="ltr" data-expanded-url="http://www.washingtonpost.com/business/economy/value-added-mosquito-control-business-scratches-this-entrepreneurs-itch/2012/06/10/gJQA43p6SV_story.html" class="twitter-timeline-link u-hidden" target="_blank" title="http://www.washingtonpost.com/business/economy/value-added-mosquito-control-business-scratches-this-entrepreneurs-itch/2012/06/10/gJQA43p6SV_story.html" ><span class="tco-ellipsis"></span><span class="invisible">http://www.</span><span class="js-display-url">washingtonpost.com/business/econo</span><span class="invisible">my/value-added-mosquito-control-business-scratches-this-entrepreneurs-itch/2012/06/10/gJQA43p6SV_story.html</span><span class="tco-ellipsis"><span class="invisible">&nbsp;</span>…</span></a>]]></document>
		<document id="215257012580261889" url="https://twitter.com/LauraHarders/status/215257012580261889"><![CDATA[<a href="/DanaMarieAdams" class="twitter-atreply pretty-link js-nav" dir="ltr" data-mentioned-user-id="208836648" ><s>@</s><b>DanaMarieAdams</b></a> great feature on <a href="/savvyblogging" class="twitter-atreply pretty-link js-nav" dir="ltr" data-mentioned-user-id="1635680065" ><s>@</s><b>SavvyBlogging</b></a> yesterday! Will you be at <a href="/hashtag/SBSummit?src=hash" data-query-source="hashtag_click" class="twitter-hashtag pretty-link js-nav" dir="ltr" ><s>#</s><b>SBSummit</b></a> in October?]]></document>
		<document id="227377599821778946" url="https://twitter.com/LauraHarders/status/227377599821778946"><![CDATA[Excited for <a href="/DecksPorchesMD" class="twitter-atreply pretty-link js-nav" dir="ltr" data-mentioned-user-id="271973293" ><s>@</s><b>DecksPorchesMD</b></a>&#39;s feature in <a href="/addedvalueth" class="twitter-atreply pretty-link js-nav" dir="ltr" data-mentioned-user-id="21792943" ><s>@</s><b>AddedValueTH</b></a>&#39;s <a href="/washpostbiz" class="twitter-atreply pretty-link js-nav" dir="ltr" data-mentioned-user-id="16909907" ><s>@</s><b>WashPostBiz</b></a> column! &quot;An electrical engineer’s path to...&quot;<a href="http://t.co/a0Ct4D01" rel="nofollow noopener" dir="ltr" data-expanded-url="http://wapo.st/PC2WuE" class="twitter-timeline-link u-hidden" target="_blank" title="http://wapo.st/PC2WuE" ><span class="tco-ellipsis"></span><span class="invisible">http://</span><span class="js-display-url">wapo.st/PC2WuE</span><span class="invisible"></span><span class="tco-ellipsis"><span class="invisible">&nbsp;</span></span></a>]]></document>
		<document id="227871246841421824" url="https://twitter.com/LauraHarders/status/227871246841421824"><![CDATA[Oy! RT <a href="/addedvalueth" class="twitter-atreply pretty-link js-nav" dir="ltr" data-mentioned-user-id="21792943" ><s>@</s><b>addedvalueth</b></a>: RT <a href="/Clarabridge" class="twitter-atreply pretty-link js-nav" dir="ltr" data-mentioned-user-id="18339273" ><s>@</s><b>Clarabridge</b></a>: New study shows 70% of Fortune 500 CEOs w/out <a href="/hashtag/socialmedia?src=hash" data-query-source="hashtag_click" class="twitter-hashtag pretty-link js-nav" dir="ltr" ><s>#</s><b>socialmedia</b></a> presence. <a href="http://t.co/bxVJ6kem" rel="nofollow noopener" dir="ltr" data-expanded-url="http://bit.ly/PWexug" class="twitter-timeline-link" target="_blank" title="http://bit.ly/PWexug" ><span class="tco-ellipsis"></span><span class="invisible">http://</span><span class="js-display-url">bit.ly/PWexug</span><span class="invisible"></span><span class="tco-ellipsis"><span class="invisible">&nbsp;</span></span></a> <a href="/hashtag/CRM?src=hash" data-query-source="hashtag_click" class="twitter-hashtag pretty-link js-nav" dir="ltr" ><s>#</s><b>CRM</b></a>]]></document>
		<document id="228616655125745665" url="https://twitter.com/LauraHarders/status/228616655125745665"><![CDATA[Love the comments on <a href="/DecksPorchesMD" class="twitter-atreply pretty-link js-nav" dir="ltr" data-mentioned-user-id="271973293" ><s>@</s><b>DecksPorchesMD</b></a>&#39;s feature in <a href="/addedvalueth" class="twitter-atreply pretty-link js-nav" dir="ltr" data-mentioned-user-id="21792943" ><s>@</s><b>AddedValueTH</b></a>&#39;s column. &quot;Jack-of-All-Tradery&quot; &quot;Slam Dunk Choice&quot;...<a href="http://t.co/a0Ct4D01" rel="nofollow noopener" dir="ltr" data-expanded-url="http://wapo.st/PC2WuE" class="twitter-timeline-link u-hidden" target="_blank" title="http://wapo.st/PC2WuE" ><span class="tco-ellipsis"></span><span class="invisible">http://</span><span class="js-display-url">wapo.st/PC2WuE</span><span class="invisible"></span><span class="tco-ellipsis"><span class="invisible">&nbsp;</span></span></a>]]></document>
		<document id="240163361051000833" url="https://twitter.com/LauraHarders/status/240163361051000833"><![CDATA[Great tips from <a href="/MosquitoMDsquad" class="twitter-atreply pretty-link js-nav" dir="ltr" data-mentioned-user-id="521887099" ><s>@</s><b>MosquitoMDSquad</b></a> owner John Barrett on @news8newstalk! <a href="http://t.co/5cEf1zCS" rel="nofollow noopener" dir="ltr" data-expanded-url="http://www.tbd.com/blogs/news-talk/2012/08/rnc-preview-smart-meter-fight-west-nile-virus-16525.html" class="twitter-timeline-link" target="_blank" title="http://www.tbd.com/blogs/news-talk/2012/08/rnc-preview-smart-meter-fight-west-nile-virus-16525.html" ><span class="tco-ellipsis"></span><span class="invisible">http://www.</span><span class="js-display-url">tbd.com/blogs/news-tal</span><span class="invisible">k/2012/08/rnc-preview-smart-meter-fight-west-nile-virus-16525.html</span><span class="tco-ellipsis"><span class="invisible">&nbsp;</span>…</span></a> via <a href="/NewsChannel8" class="twitter-atreply pretty-link js-nav" dir="ltr" data-mentioned-user-id="250556430" ><s>@</s><b>newschannel8</b></a> Video: <a href="http://t.co/3HNumVCu" rel="nofollow noopener" dir="ltr" data-expanded-url="http://bit.ly/One5j7" class="twitter-timeline-link" target="_blank" title="http://bit.ly/One5j7" ><span class="tco-ellipsis"></span><span class="invisible">http://</span><span class="js-display-url">bit.ly/One5j7</span><span class="invisible"></span><span class="tco-ellipsis"><span class="invisible">&nbsp;</span></span></a>]]></document>
		<document id="256609549832830977" url="https://twitter.com/LauraHarders/status/256609549832830977"><![CDATA[Congrats to Damien &amp; <a href="/DCMosquitoSquad" class="twitter-atreply pretty-link js-nav" dir="ltr" data-mentioned-user-id="116802083" ><s>@</s><b>DCMosquitoSquad</b></a> on the <a href="/Infusionsoft" class="twitter-atreply pretty-link js-nav" dir="ltr" data-mentioned-user-id="14837385" ><s>@</s><b>InfusionSoft</b></a> feature! &quot;Taking the Sting Out of Pest Control&quot; <a href="http://t.co/PmrPDhO6" rel="nofollow noopener" dir="ltr" data-expanded-url="http://www.infusionblog.com/infusionsoft-company-buzz/taking-the-sting-out-of-pest-control-damien-sanchez/" class="twitter-timeline-link" target="_blank" title="http://www.infusionblog.com/infusionsoft-company-buzz/taking-the-sting-out-of-pest-control-damien-sanchez/" ><span class="tco-ellipsis"></span><span class="invisible">http://www.</span><span class="js-display-url">infusionblog.com/infusionsoft-c</span><span class="invisible">ompany-buzz/taking-the-sting-out-of-pest-control-damien-sanchez/</span><span class="tco-ellipsis"><span class="invisible">&nbsp;</span>…</span></a>]]></document>
		<document id="257893512194961408" url="https://twitter.com/LauraHarders/status/257893512194961408"><![CDATA[Congrats Damien &amp; team! RT <a href="/DCMosquitoSquad" class="twitter-atreply pretty-link js-nav" dir="ltr" data-mentioned-user-id="116802083" ><s>@</s><b>DCMosquitoSquad</b></a>: Check out our <a href="/VOANews" class="twitter-atreply pretty-link js-nav" dir="ltr" data-mentioned-user-id="16273831" ><s>@</s><b>VOANews</b></a> feature &quot;West Nile Surge Keeps Exterminator Busy&quot; <a href="http://t.co/57upy1Oz" rel="nofollow noopener" dir="ltr" data-expanded-url="http://ow.ly/eujBa" class="twitter-timeline-link" target="_blank" title="http://ow.ly/eujBa" ><span class="tco-ellipsis"></span><span class="invisible">http://</span><span class="js-display-url">ow.ly/eujBa</span><span class="invisible"></span><span class="tco-ellipsis"><span class="invisible">&nbsp;</span></span></a>]]></document>
		<document id="258941604205838336" url="https://twitter.com/LauraHarders/status/258941604205838336"><![CDATA[<a href="/mchadwickMG" class="twitter-atreply pretty-link js-nav" dir="ltr" data-mentioned-user-id="18056058" ><s>@</s><b>mchadwickMG</b></a> great to see you! Hope to chat more today during the summit!]]></document>
		<document id="258943651420446720" url="https://twitter.com/LauraHarders/status/258943651420446720"><![CDATA[Be an evangelist of risk in developing your brand: be an advocate of courage <a href="/hashtag/MAMsummit?src=hash" data-query-source="hashtag_click" class="twitter-hashtag pretty-link js-nav" dir="ltr" ><s>#</s><b>MAMsummit</b></a> <a href="/hashtag/CMO?src=hash" data-query-source="hashtag_click" class="twitter-hashtag pretty-link js-nav" dir="ltr" ><s>#</s><b>CMO</b></a>]]></document>
		<document id="258946177150619648" url="https://twitter.com/LauraHarders/status/258946177150619648"><![CDATA[Be relevant to consumers on their most used device or platform <a href="/hashtag/userexperience?src=hash" data-query-source="hashtag_click" class="twitter-hashtag pretty-link js-nav" dir="ltr" ><s>#</s><b>userexperience</b></a> <a href="/hashtag/MAMsummit?src=hash" data-query-source="hashtag_click" class="twitter-hashtag pretty-link js-nav" dir="ltr" ><s>#</s><b>MAMsummit</b></a>]]></document>
		<document id="258963794993233920" url="https://twitter.com/LauraHarders/status/258963794993233920"><![CDATA[<a href="/TuvelComms" class="twitter-atreply pretty-link js-nav" dir="ltr" data-mentioned-user-id="144963227" ><s>@</s><b>TuvelComms</b></a> <a href="/mitcharno" class="twitter-atreply pretty-link js-nav" dir="ltr" data-mentioned-user-id="10012282" ><s>@</s><b>mitcharno</b></a> so nice to meet you in person! Thrilled to be here &amp; looking fwd to your &quot;Is FB losing its cool?&#39; session <a href="/hashtag/MAMsummit?src=hash" data-query-source="hashtag_click" class="twitter-hashtag pretty-link js-nav" dir="ltr" ><s>#</s><b>MAMsummit</b></a>]]></document>
		<document id="258995938117423105" url="https://twitter.com/LauraHarders/status/258995938117423105"><![CDATA[Great points on Facebook &quot;perception of privacy&quot; via  <a href="/mitcharno" class="twitter-atreply pretty-link js-nav" dir="ltr" data-mentioned-user-id="10012282" ><s>@</s><b>mitcharno</b></a> <a href="/TuvelComms" class="twitter-atreply pretty-link js-nav" dir="ltr" data-mentioned-user-id="144963227" ><s>@</s><b>TuvelComms</b></a> <a href="/hashtag/mamsummit?src=hash" data-query-source="hashtag_click" class="twitter-hashtag pretty-link js-nav" dir="ltr" ><s>#</s><b>mamsummit</b></a> <a href="/hashtag/fb?src=hash" data-query-source="hashtag_click" class="twitter-hashtag pretty-link js-nav" dir="ltr" ><s>#</s><b>fb</b></a>]]></document>
		<document id="259042899461824512" url="https://twitter.com/LauraHarders/status/259042899461824512"><![CDATA[<a href="/GraceAndLux" class="twitter-atreply pretty-link js-nav" dir="ltr" data-mentioned-user-id="344887750" ><s>@</s><b>GraceAndLux</b></a> don&#39;t be jealous, but I got to hang out w/ <a href="/mchadwickMG" class="twitter-atreply pretty-link js-nav" dir="ltr" data-mentioned-user-id="18056058" ><s>@</s><b>mchadwickMG</b></a> today! We agreed, the 3 of us need to meetup soon! <a href="/hashtag/UVAalums?src=hash" data-query-source="hashtag_click" class="twitter-hashtag pretty-link js-nav" dir="ltr" ><s>#</s><b>UVAalums</b></a>]]></document>
		<document id="261184462883266560" url="https://twitter.com/LauraHarders/status/261184462883266560"><![CDATA[Congrats <a href="/DCMosquitoSquad" class="twitter-atreply pretty-link js-nav" dir="ltr" data-mentioned-user-id="116802083" ><s>@</s><b>DCMosquitoSquad</b></a> on mention in <a href="/businessonmain" class="twitter-atreply pretty-link js-nav" dir="ltr" data-mentioned-user-id="159302049" ><s>@</s><b>businessonmain</b></a> &#39;How to Handle Negative Customer Reviews&#39; - tough subject! <a href="http://t.co/y2gtpnT0" rel="nofollow noopener" dir="ltr" data-expanded-url="http://on-msn.com/RDn9mt" class="twitter-timeline-link" target="_blank" title="http://on-msn.com/RDn9mt" ><span class="tco-ellipsis"></span><span class="invisible">http://</span><span class="js-display-url">on-msn.com/RDn9mt</span><span class="invisible"></span><span class="tco-ellipsis"><span class="invisible">&nbsp;</span></span></a>]]></document>
		<document id="264723847746555904" url="https://twitter.com/LauraHarders/status/264723847746555904"><![CDATA[Did you catch me on <a href="/wusa9" class="twitter-atreply pretty-link js-nav" dir="ltr" data-mentioned-user-id="15391102" ><s>@</s><b>wusa9</b></a> 9NewsNow at 5 yesterday? Loved sharing how to Maximize Your Grocery Coupon Savings <a href="http://t.co/13FfljSb" rel="nofollow noopener" dir="ltr" data-expanded-url="http://on.wusa9.com/SF0Mjp" class="twitter-timeline-link" target="_blank" title="http://on.wusa9.com/SF0Mjp" ><span class="tco-ellipsis"></span><span class="invisible">http://</span><span class="js-display-url">on.wusa9.com/SF0Mjp</span><span class="invisible"></span><span class="tco-ellipsis"><span class="invisible">&nbsp;</span></span></a>]]></document>
		<document id="268799408357920770" url="https://twitter.com/LauraHarders/status/268799408357920770"><![CDATA[10 ways to fight Turkey Day gouge via <a href="/MSN_Money" class="twitter-atreply pretty-link js-nav" dir="ltr" data-mentioned-user-id="40533912" ><s>@</s><b>MSN_Money</b></a> <a href="http://t.co/9lHiMxJw" rel="nofollow noopener" dir="ltr" data-expanded-url="http://on-msn.com/X5ZstK" class="twitter-timeline-link" target="_blank" title="http://on-msn.com/X5ZstK" ><span class="tco-ellipsis"></span><span class="invisible">http://</span><span class="js-display-url">on-msn.com/X5ZstK</span><span class="invisible"></span><span class="tco-ellipsis"><span class="invisible">&nbsp;</span></span></a> - features <a href="/BeltwayBargain" class="twitter-atreply pretty-link js-nav" dir="ltr" data-mentioned-user-id="114085960" ><s>@</s><b>BeltwayBargain</b></a> <a href="/SavinFamlyMoney" class="twitter-atreply pretty-link js-nav" dir="ltr" data-mentioned-user-id="17479700" ><s>@</s><b>SavinFamlyMoney</b></a> <a href="/LHLiving" class="twitter-atreply pretty-link js-nav" dir="ltr" data-mentioned-user-id="49871286" ><s>@</s><b>lhliving</b></a> @LisaLightnerLL]]></document>
		<document id="270548187373268992" url="https://twitter.com/LauraHarders/status/270548187373268992"><![CDATA[Thanksgiving on a budget: <a href="/BeltwayBargain" class="twitter-atreply pretty-link js-nav" dir="ltr" data-mentioned-user-id="114085960" ><s>@</s><b>BeltwayBargain</b></a> coupon tips featured on <a href="/ABC7News" class="twitter-atreply pretty-link js-nav" dir="ltr" data-mentioned-user-id="14897840" ><s>@</s><b>abc7news</b></a>: <a href="http://t.co/K9qmtZBN" rel="nofollow noopener" dir="ltr" data-expanded-url="http://www.wjla.com/articles/2012/11/thanksgiving-on-a-budget-beltway-bargain-mom-s-coupon-tips-82128.html#.UKpN0d8-dgE.twitter" class="twitter-timeline-link" target="_blank" title="http://www.wjla.com/articles/2012/11/thanksgiving-on-a-budget-beltway-bargain-mom-s-coupon-tips-82128.html#.UKpN0d8-dgE.twitter" ><span class="tco-ellipsis"></span><span class="invisible">http://www.</span><span class="js-display-url">wjla.com/articles/2012/</span><span class="invisible">11/thanksgiving-on-a-budget-beltway-bargain-mom-s-coupon-tips-82128.html#.UKpN0d8-dgE.twitter</span><span class="tco-ellipsis"><span class="invisible">&nbsp;</span>…</span></a> <a href="/hashtag/DC?src=hash" data-query-source="hashtag_click" class="twitter-hashtag pretty-link js-nav" dir="ltr" ><s>#</s><b>DC</b></a> <a href="/hashtag/Thanksgiving?src=hash" data-query-source="hashtag_click" class="twitter-hashtag pretty-link js-nav" dir="ltr" ><s>#</s><b>Thanksgiving</b></a>]]></document>
		<document id="270901172611723269" url="https://twitter.com/LauraHarders/status/270901172611723269"><![CDATA[Thanksgiving on a budget, best deals in <a href="/hashtag/DC?src=hash" data-query-source="hashtag_click" class="twitter-hashtag pretty-link js-nav" dir="ltr" ><s>#</s><b>DC</b></a> area: <a href="http://t.co/3iuISMgy" rel="nofollow noopener" dir="ltr" data-expanded-url="http://www.wjla.com/articles/2012/11/thanksgiving-on-a-budget-best-deals-in-d-c-area-82241.html#.UKuWvUb5ggQ.twitter" class="twitter-timeline-link" target="_blank" title="http://www.wjla.com/articles/2012/11/thanksgiving-on-a-budget-best-deals-in-d-c-area-82241.html#.UKuWvUb5ggQ.twitter" ><span class="tco-ellipsis"></span><span class="invisible">http://www.</span><span class="js-display-url">wjla.com/articles/2012/</span><span class="invisible">11/thanksgiving-on-a-budget-best-deals-in-d-c-area-82241.html#.UKuWvUb5ggQ.twitter</span><span class="tco-ellipsis"><span class="invisible">&nbsp;</span>…</span></a> via <a href="/ABC7News" class="twitter-atreply pretty-link js-nav" dir="ltr" data-mentioned-user-id="14897840" ><s>@</s><b>abc7news</b></a> <a href="/BeltwayBargain" class="twitter-atreply pretty-link js-nav" dir="ltr" data-mentioned-user-id="114085960" ><s>@</s><b>BeltwayBargain</b></a>]]></document>
		<document id="271276882748637184" url="https://twitter.com/LauraHarders/status/271276882748637184"><![CDATA[Thanksgiving on a budget! <a href="/BeltwayBargain" class="twitter-atreply pretty-link js-nav" dir="ltr" data-mentioned-user-id="114085960" ><s>@</s><b>BeltwayBargain</b></a> shares last-minute coupon tips: <a href="http://t.co/3wDH3ng7" rel="nofollow noopener" dir="ltr" data-expanded-url="http://www.wjla.com/articles/2012/11/thanksgiving-on-a-budget-beltway-bargain-mom-laura-harders-last-minute-coupon-tips-82230.html#.UKzzVeQ5SAY.twitter" class="twitter-timeline-link" target="_blank" title="http://www.wjla.com/articles/2012/11/thanksgiving-on-a-budget-beltway-bargain-mom-laura-harders-last-minute-coupon-tips-82230.html#.UKzzVeQ5SAY.twitter" ><span class="tco-ellipsis"></span><span class="invisible">http://www.</span><span class="js-display-url">wjla.com/articles/2012/</span><span class="invisible">11/thanksgiving-on-a-budget-beltway-bargain-mom-laura-harders-last-minute-coupon-tips-82230.html#.UKzzVeQ5SAY.twitter</span><span class="tco-ellipsis"><span class="invisible">&nbsp;</span>…</span></a> via <a href="/ABC7News" class="twitter-atreply pretty-link js-nav" dir="ltr" data-mentioned-user-id="14897840" ><s>@</s><b>abc7news</b></a>]]></document>
		<document id="273946212535767041" url="https://twitter.com/LauraHarders/status/273946212535767041"><![CDATA[Cyber Monday deals (or ANYTIME online shopping tips!) on <a href="/LetsTalkLiveDC" class="twitter-atreply pretty-link js-nav" dir="ltr" data-mentioned-user-id="519818027" ><s>@</s><b>LetsTalkLiveDC</b></a> <a href="http://t.co/2jyaVYOh" rel="nofollow noopener" dir="ltr" data-expanded-url="http://www.wjla.com/blogs/lets-talk-live/2012/11/cyber-monday-deals-17302.html#.ULarIUFyHp8.twitter" class="twitter-timeline-link" target="_blank" title="http://www.wjla.com/blogs/lets-talk-live/2012/11/cyber-monday-deals-17302.html#.ULarIUFyHp8.twitter" ><span class="tco-ellipsis"></span><span class="invisible">http://www.</span><span class="js-display-url">wjla.com/blogs/lets-tal</span><span class="invisible">k-live/2012/11/cyber-monday-deals-17302.html#.ULarIUFyHp8.twitter</span><span class="tco-ellipsis"><span class="invisible">&nbsp;</span>…</span></a> via <a href="/ABC7News" class="twitter-atreply pretty-link js-nav" dir="ltr" data-mentioned-user-id="14897840" ><s>@</s><b>abc7news</b></a> <a href="/BeltwayBargain" class="twitter-atreply pretty-link js-nav" dir="ltr" data-mentioned-user-id="114085960" ><s>@</s><b>beltwaybargain</b></a>]]></document>
		<document id="276417868155994112" url="https://twitter.com/LauraHarders/status/276417868155994112"><![CDATA[:) RT <a href="/MarkGund" class="twitter-atreply pretty-link js-nav" dir="ltr" data-mentioned-user-id="19923759" ><s>@</s><b>MarkGund</b></a>: <a href="/DVyo" class="twitter-atreply pretty-link js-nav" dir="ltr" data-mentioned-user-id="13346322" ><s>@</s><b>DVyo</b></a> Excellent! <a href="http://t.co/5ZErKJLp" rel="nofollow noopener" dir="ltr" data-expanded-url="http://www.youtube.com/watch?v=RXuYSvxd0sE" class="twitter-timeline-link" target="_blank" title="http://www.youtube.com/watch?v=RXuYSvxd0sE" ><span class="tco-ellipsis"></span><span class="invisible">http://www.</span><span class="js-display-url">youtube.com/watch?v=RXuYSv</span><span class="invisible">xd0sE</span><span class="tco-ellipsis"><span class="invisible">&nbsp;</span>…</span></a> <a href="/LauraHarders" class="twitter-atreply pretty-link js-nav" dir="ltr" data-mentioned-user-id="355866661" ><s>@</s><b>LauraHarders</b></a>]]></document>
		<document id="296691884418560001" url="https://twitter.com/LauraHarders/status/296691884418560001"><![CDATA[<a href="/itsandrewhorn" class="twitter-atreply pretty-link js-nav" dir="ltr" data-mentioned-user-id="16643569" ><s>@</s><b>itsandrewhorn</b></a> I&#39;d recommend <a href="/SaraFimiani" class="twitter-atreply pretty-link js-nav" dir="ltr" data-mentioned-user-id="287393289" ><s>@</s><b>sarafimiani</b></a> who runs Fitness Advantage <a href="http://t.co/jXeOFOH0" rel="nofollow noopener" dir="ltr" data-expanded-url="http://www.fitnessadvantage.us/" class="twitter-timeline-link" target="_blank" title="http://www.fitnessadvantage.us/" ><span class="tco-ellipsis"></span><span class="invisible">http://www.</span><span class="js-display-url">fitnessadvantage.us</span><span class="invisible">/</span><span class="tco-ellipsis"><span class="invisible">&nbsp;</span></span></a> - great personal trainer in NOVA!]]></document>
		<document id="296692508954619904" url="https://twitter.com/LauraHarders/status/296692508954619904"><![CDATA[10 Extreme Couponing Tips for the Casual Consumer via <a href="/mint" class="twitter-atreply pretty-link js-nav" dir="ltr" data-mentioned-user-id="13796572" ><s>@</s><b>mint</b></a> --featuring tips from <a href="/BeltwayBargain" class="twitter-atreply pretty-link js-nav" dir="ltr" data-mentioned-user-id="114085960" ><s>@</s><b>BeltwayBargain</b></a> (moi!) <a href="http://t.co/S6e30KIp" rel="nofollow noopener" dir="ltr" data-expanded-url="http://www.mint.com/blog/consumer-iq/10-extreme-couponing-tips-for-the-casual-consumer-0113/" class="twitter-timeline-link" target="_blank" title="http://www.mint.com/blog/consumer-iq/10-extreme-couponing-tips-for-the-casual-consumer-0113/" ><span class="tco-ellipsis"></span><span class="invisible">http://www.</span><span class="js-display-url">mint.com/blog/consumer-</span><span class="invisible">iq/10-extreme-couponing-tips-for-the-casual-consumer-0113/</span><span class="tco-ellipsis"><span class="invisible">&nbsp;</span>…</span></a>]]></document>
		<document id="298822849316134912" url="https://twitter.com/LauraHarders/status/298822849316134912"><![CDATA[My Funny Valentine: 4 humorous DIY Cards created by <a href="/BeltwayBargain" class="twitter-atreply pretty-link js-nav" dir="ltr" data-mentioned-user-id="114085960" ><s>@</s><b>BeltwayBargain</b></a> for <a href="/Valpakcoupons" class="twitter-atreply pretty-link js-nav" dir="ltr" data-mentioned-user-id="14433949" ><s>@</s><b>ValpakCoupons</b></a> Blog <a href="http://t.co/Z9DYnSq3" rel="nofollow noopener" dir="ltr" data-expanded-url="http://www.valpak.com/blog/my-funny-valentine-4-diy-cards/" class="twitter-timeline-link" target="_blank" title="http://www.valpak.com/blog/my-funny-valentine-4-diy-cards/" ><span class="tco-ellipsis"></span><span class="invisible">http://www.</span><span class="js-display-url">valpak.com/blog/my-funny-</span><span class="invisible">valentine-4-diy-cards/</span><span class="tco-ellipsis"><span class="invisible">&nbsp;</span>…</span></a> <a href="/hashtag/lovetosave?src=hash" data-query-source="hashtag_click" class="twitter-hashtag pretty-link js-nav" dir="ltr" ><s>#</s><b>lovetosave</b></a>]]></document>
		<document id="304633386973143040" url="https://twitter.com/LauraHarders/status/304633386973143040"><![CDATA[That&#39;s my hubby <a href="/PatHarders" class="twitter-atreply pretty-link js-nav" dir="ltr" data-mentioned-user-id="114096011" ><s>@</s><b>PatHarders</b></a>! RT <a href="/SislersStone" class="twitter-atreply pretty-link js-nav" dir="ltr" data-mentioned-user-id="210863974" ><s>@</s><b>SislersStone</b></a>: <a href="/EnlightenLights" class="twitter-atreply pretty-link js-nav" dir="ltr" data-mentioned-user-id="384039311" ><s>@</s><b>EnlightenLights</b></a> installing our lights at <a href="/hashtag/Dulles?src=hash" data-query-source="hashtag_click" class="twitter-hashtag pretty-link js-nav" dir="ltr" ><s>#</s><b>Dulles</b></a> @dchomeshows<a href="http://t.co/0UjVZG5sGd" class="twitter-timeline-link u-hidden" data-pre-embedded="true" dir="ltr" >pic.twitter.com/0UjVZG5sGd</a>]]></document>
		<document id="312009880347222016" url="https://twitter.com/LauraHarders/status/312009880347222016"><![CDATA[That moment when you wonder why that celebrity RT&#39;ed your client&#39;s tweet (that you wrote) to his 475K fans <a href="/hashtag/pleasantlyperplexed?src=hash" data-query-source="hashtag_click" class="twitter-hashtag pretty-link js-nav" dir="ltr" ><s>#</s><b>pleasantlyperplexed</b></a> <a href="/hashtag/ftw?src=hash" data-query-source="hashtag_click" class="twitter-hashtag pretty-link js-nav" dir="ltr" ><s>#</s><b>ftw</b></a>]]></document>
		<document id="314117529306025984" url="https://twitter.com/LauraHarders/status/314117529306025984"><![CDATA[Awesome! Thanks Mark! RT <a href="/MarkGund" class="twitter-atreply pretty-link js-nav" dir="ltr" data-mentioned-user-id="19923759" ><s>@</s><b>MarkGund</b></a>: 29 Tools to Enhance Your Business Blog <a href="http://t.co/zgI8RQjV50" rel="nofollow noopener" dir="ltr" data-expanded-url="http://bit.ly/10R7WD1" class="twitter-timeline-link" target="_blank" title="http://bit.ly/10R7WD1" ><span class="tco-ellipsis"></span><span class="invisible">http://</span><span class="js-display-url">bit.ly/10R7WD1</span><span class="invisible"></span><span class="tco-ellipsis"><span class="invisible">&nbsp;</span></span></a> | <a href="/jennifergerlock" class="twitter-atreply pretty-link js-nav" dir="ltr" data-mentioned-user-id="15907173" ><s>@</s><b>JenniferGerlock</b></a> <a href="/LauraHarders" class="twitter-atreply pretty-link js-nav" dir="ltr" data-mentioned-user-id="355866661" ><s>@</s><b>LauraHarders</b></a>]]></document>
		<document id="319822326642380803" url="https://twitter.com/LauraHarders/status/319822326642380803"><![CDATA[<a href="/DCMosquitoSquad" class="twitter-atreply pretty-link js-nav" dir="ltr" data-mentioned-user-id="116802083" ><s>@</s><b>DCMosquitoSquad</b></a> congrats on hitting that milestone!]]></document>
		<document id="326162134255943680" url="https://twitter.com/LauraHarders/status/326162134255943680"><![CDATA[Congrats! RT <a href="/LetMommySleep" class="twitter-atreply pretty-link js-nav" dir="ltr" data-mentioned-user-id="331144825" ><s>@</s><b>LetMommySleep</b></a>: Capital Buzz: LMS gets a blurb in the Post today! <a href="http://t.co/Guf3pn3zvn" rel="nofollow noopener" dir="ltr" data-expanded-url="http://wapo.st/17GeiXB" class="twitter-timeline-link" target="_blank" title="http://wapo.st/17GeiXB" ><span class="tco-ellipsis"></span><span class="invisible">http://</span><span class="js-display-url">wapo.st/17GeiXB</span><span class="invisible"></span><span class="tco-ellipsis"><span class="invisible">&nbsp;</span></span></a> via <a href="/addedvalueth" class="twitter-atreply pretty-link js-nav" dir="ltr" data-mentioned-user-id="21792943" ><s>@</s><b>addedvalueth</b></a> <a href="/washingtonpost" class="twitter-atreply pretty-link js-nav" dir="ltr" data-mentioned-user-id="2467791" ><s>@</s><b>washingtonpost</b></a>]]></document>
		<document id="339532070151921664" url="https://twitter.com/LauraHarders/status/339532070151921664"><![CDATA[Great to see <a href="/drkatynelson" class="twitter-atreply pretty-link js-nav" dir="ltr" data-mentioned-user-id="85095538" ><s>@</s><b>drkatynelson</b></a> &amp; <a href="/ThePetShowtv" class="twitter-atreply pretty-link js-nav" dir="ltr" data-mentioned-user-id="929986094" ><s>@</s><b>ThePetShowtv</b></a> guests <a href="/DCMosquitoSquad" class="twitter-atreply pretty-link js-nav" dir="ltr" data-mentioned-user-id="116802083" ><s>@</s><b>DCMosquitoSquad</b></a> <a href="/ASPCA" class="twitter-atreply pretty-link js-nav" dir="ltr" data-mentioned-user-id="14955908" ><s>@</s><b>aspca</b></a> <a href="/rmpatch" class="twitter-atreply pretty-link js-nav" dir="ltr" data-mentioned-user-id="109331762" ><s>@</s><b>rmpatch</b></a> <a href="/AlexAnimals" class="twitter-atreply pretty-link js-nav" dir="ltr" data-mentioned-user-id="237667678" ><s>@</s><b>AlexAnimals</b></a> today! Tune in this Sat 11am <a href="/NewsChannel8" class="twitter-atreply pretty-link js-nav" dir="ltr" data-mentioned-user-id="250556430" ><s>@</s><b>NewsChannel8</b></a>!]]></document>
		<document id="341291356460814336" url="https://twitter.com/LauraHarders/status/341291356460814336"><![CDATA[<a href="/dominos" class="twitter-atreply pretty-link js-nav" dir="ltr" data-mentioned-user-id="31444922" ><s>@</s><b>Dominos</b></a> franchisee talks biz + <a href="/Capture_Billing" class="twitter-atreply pretty-link js-nav" dir="ltr" data-mentioned-user-id="44726094" ><s>@</s><b>Capture_Billing</b></a> files 120K medical bill claims/yr <a href="http://t.co/McZ07xknek" rel="nofollow noopener" dir="ltr" data-expanded-url="http://wapo.st/15tLpPj" class="twitter-timeline-link" target="_blank" title="http://wapo.st/15tLpPj" ><span class="tco-ellipsis"></span><span class="invisible">http://</span><span class="js-display-url">wapo.st/15tLpPj</span><span class="invisible"></span><span class="tco-ellipsis"><span class="invisible">&nbsp;</span></span></a> via <a href="/washingtonpost" class="twitter-atreply pretty-link js-nav" dir="ltr" data-mentioned-user-id="2467791" ><s>@</s><b>washingtonpost</b></a> <a href="/addedvalueth" class="twitter-atreply pretty-link js-nav" dir="ltr" data-mentioned-user-id="21792943" ><s>@</s><b>addedvalueth</b></a>]]></document>
		<document id="344622922033422337" url="https://twitter.com/LauraHarders/status/344622922033422337"><![CDATA[Thanks! RT <a href="/Capture_Billing" class="twitter-atreply pretty-link js-nav" dir="ltr" data-mentioned-user-id="44726094" ><s>@</s><b>Capture_Billing</b></a>: I gave <a href="/LauraHarders" class="twitter-atreply pretty-link js-nav" dir="ltr" data-mentioned-user-id="355866661" ><s>@</s><b>LauraHarders</b></a> +Kred influence in the Marketing community<a href="http://t.co/uZRKILmJZE" rel="nofollow noopener" dir="ltr" data-expanded-url="http://kred.com/?pkid=998372" class="twitter-timeline-link u-hidden" target="_blank" title="http://kred.com/?pkid=998372" ><span class="tco-ellipsis"></span><span class="invisible">http://</span><span class="js-display-url">kred.com/?pkid=998372</span><span class="invisible"></span><span class="tco-ellipsis"><span class="invisible">&nbsp;</span></span></a>]]></document>
		<document id="357242539889270785" url="https://twitter.com/LauraHarders/status/357242539889270785"><![CDATA[Summer budget tips to help you save $$ - <a href="/BeltwayBargain" class="twitter-atreply pretty-link js-nav" dir="ltr" data-mentioned-user-id="114085960" ><s>@</s><b>BeltwayBargain</b></a> on Let&#39;s Talk Live: <a href="http://t.co/o1oYDaP6S9" rel="nofollow noopener" dir="ltr" data-expanded-url="http://www.wjla.com/blogs/lets-talk-live/2013/07/summer-budget-tips-that-will-help-you-save-money-19367.html#.UeWzP3MyXnc.twitter" class="twitter-timeline-link" target="_blank" title="http://www.wjla.com/blogs/lets-talk-live/2013/07/summer-budget-tips-that-will-help-you-save-money-19367.html#.UeWzP3MyXnc.twitter" ><span class="tco-ellipsis"></span><span class="invisible">http://www.</span><span class="js-display-url">wjla.com/blogs/lets-tal</span><span class="invisible">k-live/2013/07/summer-budget-tips-that-will-help-you-save-money-19367.html#.UeWzP3MyXnc.twitter</span><span class="tco-ellipsis"><span class="invisible">&nbsp;</span>…</span></a> via <a href="/ABC7News" class="twitter-atreply pretty-link js-nav" dir="ltr" data-mentioned-user-id="14897840" ><s>@</s><b>abc7news</b></a>]]></document>
		<document id="368810502182281217" url="https://twitter.com/LauraHarders/status/368810502182281217"><![CDATA[<a href="/SalonKhouri" class="twitter-atreply pretty-link js-nav" dir="ltr" data-mentioned-user-id="27866985" ><s>@</s><b>SalonKhouri</b></a> <a href="/BeltwayBargain" class="twitter-atreply pretty-link js-nav" dir="ltr" data-mentioned-user-id="114085960" ><s>@</s><b>BeltwayBargain</b></a> <a href="/LatestHair" class="twitter-atreply pretty-link js-nav" dir="ltr" data-mentioned-user-id="39352732" ><s>@</s><b>LatestHair</b></a> <a href="/carrieunderwood" class="twitter-atreply pretty-link js-nav" dir="ltr" data-mentioned-user-id="386244525" ><s>@</s><b>carrieunderwood</b></a> love it! Great article on why Carrie&#39;s locks are so lovely!]]></document>
		<document id="381011951075487744" url="https://twitter.com/LauraHarders/status/381011951075487744"><![CDATA[Great how-to via <a href="/SalonKhouri" class="twitter-atreply pretty-link js-nav" dir="ltr" data-mentioned-user-id="27866985" ><s>@</s><b>SalonKhouri</b></a>! MT <a href="/alywalansky" class="twitter-atreply pretty-link js-nav" dir="ltr" data-mentioned-user-id="6362172" ><s>@</s><b>alywalansky</b></a>: New for <a href="/LatestHair" class="twitter-atreply pretty-link js-nav" dir="ltr" data-mentioned-user-id="39352732" ><s>@</s><b>LatestHair</b></a>: Snag Reese Witherspoon Glam Hollywood Hairstyle<a href="http://t.co/UiV0zZoggw" rel="nofollow noopener" dir="ltr" data-expanded-url="http://po.st/GoDhEz" class="twitter-timeline-link u-hidden" target="_blank" title="http://po.st/GoDhEz" ><span class="tco-ellipsis"></span><span class="invisible">http://</span><span class="js-display-url">po.st/GoDhEz</span><span class="invisible"></span><span class="tco-ellipsis"><span class="invisible">&nbsp;</span></span></a>]]></document>
		<document id="383231461383733248" url="https://twitter.com/LauraHarders/status/383231461383733248"><![CDATA[LOL! RT <a href="/DCMosquitoSquad" class="twitter-atreply pretty-link js-nav" dir="ltr" data-mentioned-user-id="116802083" ><s>@</s><b>DCMosquitoSquad</b></a>: Say No To Mosquito Net Pants. <a href="http://t.co/QemQqbUCtu" rel="nofollow noopener" dir="ltr" data-expanded-url="http://bit.ly/18ohKI0" class="twitter-timeline-link" target="_blank" title="http://bit.ly/18ohKI0" ><span class="tco-ellipsis"></span><span class="invisible">http://</span><span class="js-display-url">bit.ly/18ohKI0</span><span class="invisible"></span><span class="tco-ellipsis"><span class="invisible">&nbsp;</span></span></a> --&gt; Call Mosquito Squad and avoid a fashion blunder!]]></document>
		<document id="387395126546694144" url="https://twitter.com/LauraHarders/status/387395126546694144"><![CDATA[Catch <a href="/myCareLuLu" class="twitter-atreply pretty-link js-nav" dir="ltr" data-mentioned-user-id="980626794" ><s>@</s><b>myCareLuLu</b></a> on <a href="/LetsTalkLiveDC" class="twitter-atreply pretty-link js-nav" dir="ltr" data-mentioned-user-id="519818027" ><s>@</s><b>LetsTalkLiveDC</b></a> tomorrow 11am! They&#39;ll be sharing Q&#39;s to ask your childcare provider in Cold/Flu season! <a href="/hashtag/carelulucares?src=hash" data-query-source="hashtag_click" class="twitter-hashtag pretty-link js-nav" dir="ltr" ><s>#</s><b>carelulucares</b></a>]]></document>
		<document id="387905374810284033" url="https://twitter.com/LauraHarders/status/387905374810284033"><![CDATA[@BeAuthenticYou thanks! In great company <a href="/verybusymama" class="twitter-atreply pretty-link js-nav" dir="ltr" data-mentioned-user-id="3449247673" ><s>@</s><b>verybusymama</b></a> @PencilsAndPumps <a href="/MelanieNews8" class="twitter-atreply pretty-link js-nav" dir="ltr" data-mentioned-user-id="562929500" ><s>@</s><b>MelanieNews8</b></a> @MonarchCompany <a href="/KamberP31" class="twitter-atreply pretty-link js-nav" dir="ltr" data-mentioned-user-id="419894748" ><s>@</s><b>KamberP31</b></a> @Kdiariesblog <a href="/wired_momma" class="twitter-atreply pretty-link js-nav" dir="ltr" data-mentioned-user-id="43901944" ><s>@</s><b>wired_momma</b></a>]]></document>
		<document id="389455611710427136" url="https://twitter.com/LauraHarders/status/389455611710427136"><![CDATA[<a href="/myCareLuLu" class="twitter-atreply pretty-link js-nav" dir="ltr" data-mentioned-user-id="980626794" ><s>@</s><b>myCareLuLu</b></a> congrats on being a finalist for <a href="/women2" class="twitter-atreply pretty-link js-nav" dir="ltr" data-mentioned-user-id="14410280" ><s>@</s><b>women2</b></a> PITCH competition at <a href="/hashtag/w2conf13?src=hash" data-query-source="hashtag_click" class="twitter-hashtag pretty-link js-nav" dir="ltr" ><s>#</s><b>w2conf13</b></a> <a href="/hashtag/startup?src=hash" data-query-source="hashtag_click" class="twitter-hashtag pretty-link js-nav" dir="ltr" ><s>#</s><b>startup</b></a>!]]></document>
		<document id="390497988197359617" url="https://twitter.com/LauraHarders/status/390497988197359617"><![CDATA[Congrats <a href="/myCareLuLu" class="twitter-atreply pretty-link js-nav" dir="ltr" data-mentioned-user-id="980626794" ><s>@</s><b>myCareLuLu</b></a>! Women 2.0—Announces PITCH Finalist: CareLuLu <a href="http://t.co/QKnr37TyON" rel="nofollow noopener" dir="ltr" data-expanded-url="http://po.st/OyOaxU" class="twitter-timeline-link" target="_blank" title="http://po.st/OyOaxU" ><span class="tco-ellipsis"></span><span class="invisible">http://</span><span class="js-display-url">po.st/OyOaxU</span><span class="invisible"></span><span class="tco-ellipsis"><span class="invisible">&nbsp;</span></span></a> via <a href="/women2" class="twitter-atreply pretty-link js-nav" dir="ltr" data-mentioned-user-id="14410280" ><s>@</s><b>women2</b></a>]]></document>
		<document id="391191358440226816" url="https://twitter.com/LauraHarders/status/391191358440226816"><![CDATA[@BeAuthenticYou thank you! Happy <a href="/hashtag/FF?src=hash" data-query-source="hashtag_click" class="twitter-hashtag pretty-link js-nav" dir="ltr" ><s>#</s><b>FF</b></a> <a href="/MagnifiCuffs" class="twitter-atreply pretty-link js-nav" dir="ltr" data-mentioned-user-id="1600064665" ><s>@</s><b>magnificuffs</b></a> <a href="/Soulevant" class="twitter-atreply pretty-link js-nav" dir="ltr" data-mentioned-user-id="448501613" ><s>@</s><b>soulevant</b></a> <a href="/Femworking" class="twitter-atreply pretty-link js-nav" dir="ltr" data-mentioned-user-id="1126096442" ><s>@</s><b>femworking</b></a> <a href="/VirginiaColin" class="twitter-atreply pretty-link js-nav" dir="ltr" data-mentioned-user-id="209826198" ><s>@</s><b>virginiacolin</b></a> <a href="/AllHeartTrain" class="twitter-atreply pretty-link js-nav" dir="ltr" data-mentioned-user-id="463928217" ><s>@</s><b>allhearttrain</b></a> <a href="/Accounting4DC" class="twitter-atreply pretty-link js-nav" dir="ltr" data-mentioned-user-id="1135438812" ><s>@</s><b>accounting4dc</b></a> @stellaclimbs]]></document>
		<document id="392068794530557952" url="https://twitter.com/LauraHarders/status/392068794530557952"><![CDATA[Congrats to <a href="/myCareLuLu" class="twitter-atreply pretty-link js-nav" dir="ltr" data-mentioned-user-id="980626794" ><s>@</s><b>myCareLuLu</b></a> on the mention in the <a href="/washingtonpost" class="twitter-atreply pretty-link js-nav" dir="ltr" data-mentioned-user-id="2467791" ><s>@</s><b>washingtonpost</b></a>! <a href="http://t.co/ZR1ROuin6p" rel="nofollow noopener" dir="ltr" data-expanded-url="http://wapo.st/19kJSNN" class="twitter-timeline-link" target="_blank" title="http://wapo.st/19kJSNN" ><span class="tco-ellipsis"></span><span class="invisible">http://</span><span class="js-display-url">wapo.st/19kJSNN</span><span class="invisible"></span><span class="tco-ellipsis"><span class="invisible">&nbsp;</span></span></a> via <a href="/CapitalBiz" class="twitter-atreply pretty-link js-nav" dir="ltr" data-mentioned-user-id="12880222" ><s>@</s><b>capitalbiz</b></a> written by <a href="/addedvalueth" class="twitter-atreply pretty-link js-nav" dir="ltr" data-mentioned-user-id="21792943" ><s>@</s><b>addedvalueth</b></a>]]></document>
		<document id="392986835519299584" url="https://twitter.com/LauraHarders/status/392986835519299584"><![CDATA[Yay! RT <a href="/GoKidTrips" class="twitter-atreply pretty-link js-nav" dir="ltr" data-mentioned-user-id="321545777" ><s>@</s><b>GoKidTrips</b></a>: Be sure to listen to <a href="/LetMommySleep" class="twitter-atreply pretty-link js-nav" dir="ltr" data-mentioned-user-id="331144825" ><s>@</s><b>LetMommySleep</b></a> tomorrow morning 10/23 on <a href="/WTOP" class="twitter-atreply pretty-link js-nav" dir="ltr" data-mentioned-user-id="17906632" ><s>@</s><b>WTOP</b></a> sharing Daylight Savings sleep tips! <a href="/hashtag/LetMommySpeak?src=hash" data-query-source="hashtag_click" class="twitter-hashtag pretty-link js-nav" dir="ltr" ><s>#</s><b>LetMommySpeak</b></a>]]></document>
		<document id="397792656979267585" url="https://twitter.com/LauraHarders/status/397792656979267585"><![CDATA[Yay <a href="/myCareLuLu" class="twitter-atreply pretty-link js-nav" dir="ltr" data-mentioned-user-id="980626794" ><s>@</s><b>myCareLuLu</b></a>! MT <a href="/TechCrunch" class="twitter-atreply pretty-link js-nav" dir="ltr" data-mentioned-user-id="816653" ><s>@</s><b>TechCrunch</b></a>: <a href="/women2" class="twitter-atreply pretty-link js-nav" dir="ltr" data-mentioned-user-id="14410280" ><s>@</s><b>women2</b></a>, A Media Company for Female Entrepreneurship, Preps For Vegas <a href="http://t.co/d5nXg8E5fp" rel="nofollow noopener" dir="ltr" data-expanded-url="http://tcrn.ch/1efXYVx" class="twitter-timeline-link" target="_blank" title="http://tcrn.ch/1efXYVx" ><span class="tco-ellipsis"></span><span class="invisible">http://</span><span class="js-display-url">tcrn.ch/1efXYVx</span><span class="invisible"></span><span class="tco-ellipsis"><span class="invisible">&nbsp;</span></span></a> by <a href="/anthonyha" class="twitter-atreply pretty-link js-nav" dir="ltr" data-mentioned-user-id="14269152" ><s>@</s><b>anthonyha</b></a>]]></document>
		<document id="397793476185571329" url="https://twitter.com/LauraHarders/status/397793476185571329"><![CDATA[Wondering what ways you can save on child care? Some great tips &amp; resources here: <a href="http://t.co/Hmjalgo0Bh" rel="nofollow noopener" dir="ltr" data-expanded-url="http://thehappyhousewife.com/frugal-living/ways-to-save-on-child-care/#sthash.NGhLbMQ3.uxfs" class="twitter-timeline-link" target="_blank" title="http://thehappyhousewife.com/frugal-living/ways-to-save-on-child-care/#sthash.NGhLbMQ3.uxfs" ><span class="tco-ellipsis"></span><span class="invisible">http://</span><span class="js-display-url">thehappyhousewife.com/frugal-living/</span><span class="invisible">ways-to-save-on-child-care/#sthash.NGhLbMQ3.uxfs</span><span class="tco-ellipsis"><span class="invisible">&nbsp;</span>…</span></a> via <a href="/HappyHousewife" class="twitter-atreply pretty-link js-nav" dir="ltr" data-mentioned-user-id="2738832883" ><s>@</s><b>HappyHousewife</b></a>]]></document>
		<document id="400670856197599232" url="https://twitter.com/LauraHarders/status/400670856197599232"><![CDATA[<a href="/myCareLuLu" class="twitter-atreply pretty-link js-nav" dir="ltr" data-mentioned-user-id="980626794" ><s>@</s><b>myCareLuLu</b></a> <a href="/Evgeniya2" class="twitter-atreply pretty-link js-nav" dir="ltr" data-mentioned-user-id="84499035" ><s>@</s><b>Evgeniya2</b></a> knock it out of the park tomorrow &amp; Friday at <a href="/hashtag/w2conf13?src=hash" data-query-source="hashtag_click" class="twitter-hashtag pretty-link js-nav" dir="ltr" ><s>#</s><b>w2conf13</b></a> <a href="/hashtag/Pitch?src=hash" data-query-source="hashtag_click" class="twitter-hashtag pretty-link js-nav" dir="ltr" ><s>#</s><b>Pitch</b></a> competition! <a href="/hashtag/VegasBaby?src=hash" data-query-source="hashtag_click" class="twitter-hashtag pretty-link js-nav" dir="ltr" ><s>#</s><b>VegasBaby</b></a>]]></document>
		<document id="405760584471171072" url="https://twitter.com/LauraHarders/status/405760584471171072"><![CDATA[LOL! Agree RT <a href="/LetMommySleep" class="twitter-atreply pretty-link js-nav" dir="ltr" data-mentioned-user-id="331144825" ><s>@</s><b>LetMommySleep</b></a>: How does stainless steel get away w/ being called &quot;stainless&quot;? Looks like 1 giant constant stain to me. <a href="/hashtag/kids?src=hash" data-query-source="hashtag_click" class="twitter-hashtag pretty-link js-nav" dir="ltr" ><s>#</s><b>kids</b></a>]]></document>
		<document id="410053670458257408" url="https://twitter.com/LauraHarders/status/410053670458257408"><![CDATA[MT <a href="/SalonKhouri" class="twitter-atreply pretty-link js-nav" dir="ltr" data-mentioned-user-id="27866985" ><s>@</s><b>SalonKhouri</b></a>: <a href="/alywalansky" class="twitter-atreply pretty-link js-nav" dir="ltr" data-mentioned-user-id="6362172" ><s>@</s><b>alywalansky</b></a> of <a href="/LatestHair" class="twitter-atreply pretty-link js-nav" dir="ltr" data-mentioned-user-id="39352732" ><s>@</s><b>LatestHair</b></a> recently asked Jonathan how to recreate @EmWatson&#39;s super cute faux bob:<a href="http://t.co/dmUbLSoF2S" rel="nofollow noopener" dir="ltr" data-expanded-url="http://bit.ly/J6OVcE" class="twitter-timeline-link u-hidden" target="_blank" title="http://bit.ly/J6OVcE" ><span class="tco-ellipsis"></span><span class="invisible">http://</span><span class="js-display-url">bit.ly/J6OVcE</span><span class="invisible"></span><span class="tco-ellipsis"><span class="invisible">&nbsp;</span></span></a>]]></document>
		<document id="410881802400976896" url="https://twitter.com/LauraHarders/status/410881802400976896"><![CDATA[<a href="/SalonKhouri" class="twitter-atreply pretty-link js-nav" dir="ltr" data-mentioned-user-id="27866985" ><s>@</s><b>SalonKhouri</b></a> congrats on the feature! Great post by <a href="/theneonblonde" class="twitter-atreply pretty-link js-nav" dir="ltr" data-mentioned-user-id="255839820" ><s>@</s><b>theneonblonde</b></a> <a href="/SheKnows" class="twitter-atreply pretty-link js-nav" dir="ltr" data-mentioned-user-id="14297868" ><s>@</s><b>SheKnows</b></a> on crucial hair vocab for your next appt<a href="http://t.co/p2J94tId8T" rel="nofollow noopener" dir="ltr" data-expanded-url="http://bit.ly/1h0CAlL" class="twitter-timeline-link u-hidden" target="_blank" title="http://bit.ly/1h0CAlL" ><span class="tco-ellipsis"></span><span class="invisible">http://</span><span class="js-display-url">bit.ly/1h0CAlL</span><span class="invisible"></span><span class="tco-ellipsis"><span class="invisible">&nbsp;</span></span></a>]]></document>
		<document id="415894978255024129" url="https://twitter.com/LauraHarders/status/415894978255024129"><![CDATA[&#39;6 Cold Weather Beauty Tips to Live By&#39; <a href="http://t.co/YGDFsitO23" rel="nofollow noopener" dir="ltr" data-expanded-url="http://bit.ly/1ihBG7p" class="twitter-timeline-link" target="_blank" title="http://bit.ly/1ihBG7p" ><span class="tco-ellipsis"></span><span class="invisible">http://</span><span class="js-display-url">bit.ly/1ihBG7p</span><span class="invisible"></span><span class="tco-ellipsis"><span class="invisible">&nbsp;</span></span></a> featuring tip from <a href="/SalonKhouri" class="twitter-atreply pretty-link js-nav" dir="ltr" data-mentioned-user-id="27866985" ><s>@</s><b>SalonKhouri</b></a>! Article by <a href="/alywalansky" class="twitter-atreply pretty-link js-nav" dir="ltr" data-mentioned-user-id="6362172" ><s>@</s><b>alywalansky</b></a> on <a href="/dailymakeover" class="twitter-atreply pretty-link js-nav" dir="ltr" data-mentioned-user-id="749524799228153856" ><s>@</s><b>dailymakeover</b></a>]]></document>
	</documents>
</author>